{
  "$schema": "https://raw.githubusercontent.com/dineug/erd-editor/main/json-schema/schema.json",
  "version": "3.0.0",
  "settings": {
    "width": 4000,
    "height": 4000,
    "scrollTop": -1269.8055,
    "scrollLeft": -582.6306,
    "zoomLevel": 0.58,
    "show": 431,
    "database": 4,
    "databaseName": "",
    "canvasType": "ERD",
    "language": 1,
    "tableNameCase": 4,
    "columnNameCase": 2,
    "bracketType": 1,
    "relationshipDataTypeSync": true,
    "relationshipOptimization": false,
    "columnOrder": [
      1,
      2,
      4,
      8,
      16,
      32,
      64
    ],
    "maxWidthComment": -1,
    "ignoreSaveSettings": 0
  },
  "doc": {
    "tableIds": [
      "cQpUxLpOYUyxPH0YoHluk",
      "_DQoyIW0mWh4yxWzDoo-q",
      "8EodW7KK530D9bHNIN4vC",
      "ZlJvFqugz39C-zOVp8Niy",
      "QJEdFeKsrm8oSCMS_Se_k",
      "cQTtce6Cto28iUz5GpSII",
      "i1fNivitx70K1rJyaTswC",
      "C0RjPc1YqTUs69VpM8yqs",
      "4f9Z8zFWxVX8rBoWBLdhW",
      "OZtvqGyIw6mxj-R7hbeDW",
      "BNYvo6am8pGrh89TE7PeE",
      "ZD717xZ8SsmzE0VdbKCpX",
      "p0KeMVCBdrcK4MmNpbWLc",
      "SdRYuoMaQMiVi-syV-iNu",
      "PFV4tkpKUrgv3L36oIFpE"
    ],
    "relationshipIds": [
      "Wxc-MeJHW1ZT56NhwTkEY",
      "V9oI-ZK6N58bKgZvBpIWR",
      "cE2F20He112VIbFvzUl-G",
      "5f1oCKFwmtX1du7CPKK2P",
      "ThldVzlAFWhkoWyX7qM5_",
      "RCUsSrmZ20AV05whPsOdv",
      "7HsHZ77Xeld2vj0ClxbHL",
      "J0r_XiQKjQQIzQTNMrS-x",
      "2QpcLALFODdGwFpQvhSGU",
      "P4LBinmzTXAlwY7JPjiiq",
      "H-Fjlw4XC68En84lQm_iG",
      "6Jvqfa-HJP49rLv3E6wV9",
      "vBZ13bfSrtfMJrDu2oMlI",
      "Ffb7UaXenSEDOHDfCvD42",
      "3vNnu6Q5b0ul3mfZ4hUCe"
    ],
    "indexIds": [
      "_1Z0QCT9wykLMBDGwmPY9",
      "os9NW01l8H4Gna6ODq15Y",
      "vDbYEE0Td6tmT1LAo__F1",
      "GQeDEwbWBv53XAZOa3-6r",
      "lxHCGWl7d3c-4vjPLTTZW",
      "ROQiKfkchgNQ9lum0u_LU",
      "4iql7GHsUbPfQ-8IgAQP4",
      "8cVenpI_1ESF5TY5PaM89",
      "lPk3mfR8dzC4qUD4emTgA",
      "Mx5c2xDEuWE4m4hzYeQPR",
      "3wXtuYKjLJ9P0YDpkTG6c",
      "IXIlEjpm7H0op1E45opbw",
      "iqgQOG2lKNY6X2euWjYLw",
      "FtfUYi84Zm0v5zf7mXvUp",
      "zgJfD-iclW_Uk-tMJ9fkz"
    ],
    "memoIds": []
  },
  "collections": {
    "tableEntities": {
      "-R2yuTAMLKpUrH9WsHNm4": {
        "id": "-R2yuTAMLKpUrH9WsHNm4",
        "name": "TO",
        "comment": "",
        "columnIds": [],
        "seqColumnIds": [],
        "ui": {
          "x": 50,
          "y": 50,
          "zIndex": 2,
          "widthName": 60,
          "widthComment": 60,
          "color": ""
        },
        "meta": {
          "updateAt": 1736702707951,
          "createAt": 1736702707951
        }
      },
      "cQpUxLpOYUyxPH0YoHluk": {
        "id": "cQpUxLpOYUyxPH0YoHluk",
        "name": "MEMBERS",
        "comment": "ON",
        "columnIds": [
          "BhinAjCHkM-EZJ2qpB14B",
          "ujRb3EvYOYxMco1d_BGya",
          "NlxNnsXhyui5UGSYZ31IV",
          "zkYpoxxY_wQ8oFXe7QxcM",
          "gQDwcYL8XdTr4DbT3JEND",
          "xBnMXdsxV3BPD78boihEv",
          "JU0tX1DQuSvC3wPz-sGEN",
          "qaKwZqUa27TkL3CdEtqji",
          "UPXj8Y9-_oBgBOqixds_G",
          "3ia5CK-15TX_ZMuSzNdob",
          "-tslz2qAlyGvJJWyH6mXH"
        ],
        "seqColumnIds": [
          "BhinAjCHkM-EZJ2qpB14B",
          "ujRb3EvYOYxMco1d_BGya",
          "NlxNnsXhyui5UGSYZ31IV",
          "zkYpoxxY_wQ8oFXe7QxcM",
          "gQDwcYL8XdTr4DbT3JEND",
          "xBnMXdsxV3BPD78boihEv",
          "JU0tX1DQuSvC3wPz-sGEN",
          "qaKwZqUa27TkL3CdEtqji",
          "UPXj8Y9-_oBgBOqixds_G",
          "3ia5CK-15TX_ZMuSzNdob",
          "-tslz2qAlyGvJJWyH6mXH"
        ],
        "ui": {
          "x": 1463.9863,
          "y": 1967.7414,
          "zIndex": 2,
          "widthName": 60,
          "widthComment": 60,
          "color": ""
        },
        "meta": {
          "updateAt": 1736702822467,
          "createAt": 1736702707952
        }
      },
      "_DQoyIW0mWh4yxWzDoo-q": {
        "id": "_DQoyIW0mWh4yxWzDoo-q",
        "name": "ADDRESS",
        "comment": "ON",
        "columnIds": [
          "pIDdVjOp3mnUcXmR68tPu",
          "pv0TbeBEKpqzYNIwXJeIT",
          "q4wwx60Dnz3GLv7SIIG1k",
          "6yeij-QjJmRubLk-SxQXe",
          "nYGBxDGn0ERdfDkAKJO5R",
          "mDrP6teVkoodXGBiHfJUe",
          "vC-djrn-FRk9OyQjMaCns",
          "wXT3fJXmzZ8jO7z7W_9LD"
        ],
        "seqColumnIds": [
          "pIDdVjOp3mnUcXmR68tPu",
          "pv0TbeBEKpqzYNIwXJeIT",
          "q4wwx60Dnz3GLv7SIIG1k",
          "6yeij-QjJmRubLk-SxQXe",
          "nYGBxDGn0ERdfDkAKJO5R",
          "mDrP6teVkoodXGBiHfJUe",
          "vC-djrn-FRk9OyQjMaCns",
          "wXT3fJXmzZ8jO7z7W_9LD"
        ],
        "ui": {
          "x": 11.4755,
          "y": 1956.8197,
          "zIndex": 2,
          "widthName": 60,
          "widthComment": 60,
          "color": ""
        },
        "meta": {
          "updateAt": 1736702830441,
          "createAt": 1736702707953
        }
      },
      "8EodW7KK530D9bHNIN4vC": {
        "id": "8EodW7KK530D9bHNIN4vC",
        "name": "ADDRESS_MEMBER_ASS",
        "comment": "ON",
        "columnIds": [
          "_UZYBkq119OtyC2Li4acS",
          "XvmTxiDYWd8reNv6JBG1f"
        ],
        "seqColumnIds": [
          "_UZYBkq119OtyC2Li4acS",
          "XvmTxiDYWd8reNv6JBG1f"
        ],
        "ui": {
          "x": 711.3935,
          "y": 2071.3115,
          "zIndex": 2,
          "widthName": 131,
          "widthComment": 60,
          "color": ""
        },
        "meta": {
          "updateAt": 1736702831332,
          "createAt": 1736702707953
        }
      },
      "ZlJvFqugz39C-zOVp8Niy": {
        "id": "ZlJvFqugz39C-zOVp8Niy",
        "name": "RANK_PRIVILEGES",
        "comment": "ON",
        "columnIds": [
          "53WTCJSUe_-B_Zd4R5Dp_",
          "Jds6IawjmIAeVJtD3Em2e",
          "DXbgnQEp-hjITzq8OAef2",
          "eHLX5mnuaVt0UK-qfQAOw"
        ],
        "seqColumnIds": [
          "53WTCJSUe_-B_Zd4R5Dp_",
          "Jds6IawjmIAeVJtD3Em2e",
          "DXbgnQEp-hjITzq8OAef2",
          "eHLX5mnuaVt0UK-qfQAOw"
        ],
        "ui": {
          "x": 50,
          "y": 258,
          "zIndex": 2,
          "widthName": 98,
          "widthComment": 60,
          "color": ""
        },
        "meta": {
          "updateAt": 1736702707953,
          "createAt": 1736702707953
        }
      },
      "QJEdFeKsrm8oSCMS_Se_k": {
        "id": "QJEdFeKsrm8oSCMS_Se_k",
        "name": "ORS",
        "comment": "ON",
        "columnIds": [
          "tp3ydmosVp2zAr3aq-mZe",
          "iLrKWVUHb3U2UaOYC1KwL",
          "6rs_DKqDGC78tVUBATcQ0",
          "5kxByovBBYWdD-K23zLAq"
        ],
        "seqColumnIds": [
          "tp3ydmosVp2zAr3aq-mZe",
          "iLrKWVUHb3U2UaOYC1KwL",
          "6rs_DKqDGC78tVUBATcQ0",
          "5kxByovBBYWdD-K23zLAq"
        ],
        "ui": {
          "x": 528.9747,
          "y": 242.8101,
          "zIndex": 2,
          "widthName": 60,
          "widthComment": 60,
          "color": ""
        },
        "meta": {
          "updateAt": 1736702727102,
          "createAt": 1736702707953
        }
      },
      "cQTtce6Cto28iUz5GpSII": {
        "id": "cQTtce6Cto28iUz5GpSII",
        "name": "PATROL",
        "comment": "ON",
        "columnIds": [
          "jGU9HI-YFyQ9eNhgb1SdC",
          "PLrSDDg8rE93d4UUU7KdC",
          "XRdIym3dC9bVp7iovgy19"
        ],
        "seqColumnIds": [
          "jGU9HI-YFyQ9eNhgb1SdC",
          "PLrSDDg8rE93d4UUU7KdC",
          "XRdIym3dC9bVp7iovgy19"
        ],
        "ui": {
          "x": 949,
          "y": 50,
          "zIndex": 2,
          "widthName": 60,
          "widthComment": 60,
          "color": ""
        },
        "meta": {
          "updateAt": 1736702707954,
          "createAt": 1736702707954
        }
      },
      "i1fNivitx70K1rJyaTswC": {
        "id": "i1fNivitx70K1rJyaTswC",
        "name": "MEETING",
        "comment": "ON",
        "columnIds": [
          "D3vHPrhI4epynrutXEsb4",
          "61-sqQLNZyBzj3qyPAqQ1",
          "m6eIJyLVOZV0CvjNu8HYN",
          "Lzcu_RWaPnSpqReq4cY-m",
          "4pIstWXyGtnIEAoAYohBA",
          "mIj384ymoiJVYzINDjrsU"
        ],
        "seqColumnIds": [
          "D3vHPrhI4epynrutXEsb4",
          "61-sqQLNZyBzj3qyPAqQ1",
          "m6eIJyLVOZV0CvjNu8HYN",
          "Lzcu_RWaPnSpqReq4cY-m",
          "4pIstWXyGtnIEAoAYohBA",
          "mIj384ymoiJVYzINDjrsU"
        ],
        "ui": {
          "x": 50,
          "y": 746,
          "zIndex": 2,
          "widthName": 60,
          "widthComment": 60,
          "color": ""
        },
        "meta": {
          "updateAt": 1736702707954,
          "createAt": 1736702707954
        }
      },
      "C0RjPc1YqTUs69VpM8yqs": {
        "id": "C0RjPc1YqTUs69VpM8yqs",
        "name": "GATHERING_REPORTS",
        "comment": "ON",
        "columnIds": [
          "5qrz9OylEkRFN2lzLGIMt",
          "pug3YHd23o0zInC9m4nT3",
          "pyc8UEooyewc6SbjmsJSQ",
          "JQYN-i48j14DjN2aLyhVF",
          "TFZGWRB2fNfJvCpu7yq62",
          "MRSE6r5H43vr24b5q1pNl"
        ],
        "seqColumnIds": [
          "5qrz9OylEkRFN2lzLGIMt",
          "pug3YHd23o0zInC9m4nT3",
          "pyc8UEooyewc6SbjmsJSQ",
          "JQYN-i48j14DjN2aLyhVF",
          "TFZGWRB2fNfJvCpu7yq62",
          "MRSE6r5H43vr24b5q1pNl"
        ],
        "ui": {
          "x": 611,
          "y": 746,
          "zIndex": 2,
          "widthName": 119,
          "widthComment": 60,
          "color": ""
        },
        "meta": {
          "updateAt": 1736702707954,
          "createAt": 1736702707954
        }
      },
      "4f9Z8zFWxVX8rBoWBLdhW": {
        "id": "4f9Z8zFWxVX8rBoWBLdhW",
        "name": "EVENTS",
        "comment": "ON",
        "columnIds": [
          "-Dib_cMyUHkBlVZpEQhdj",
          "JeHFLXSbxkJZt3tjiJhXn",
          "kQ32JA5h52__SNrgXvfUN",
          "-jTVx9Bs0kqh0Ky9HIWLO",
          "nF4f_oQyPaBM32uzGKVHV",
          "SQ-cv5LxbPDagqOlPhVjj"
        ],
        "seqColumnIds": [
          "-Dib_cMyUHkBlVZpEQhdj",
          "JeHFLXSbxkJZt3tjiJhXn",
          "kQ32JA5h52__SNrgXvfUN",
          "-jTVx9Bs0kqh0Ky9HIWLO",
          "nF4f_oQyPaBM32uzGKVHV",
          "SQ-cv5LxbPDagqOlPhVjj"
        ],
        "ui": {
          "x": 1856.3793,
          "y": 1078.7586,
          "zIndex": 2,
          "widthName": 60,
          "widthComment": 60,
          "color": ""
        },
        "meta": {
          "updateAt": 1736702834468,
          "createAt": 1736702707954
        }
      },
      "OZtvqGyIw6mxj-R7hbeDW": {
        "id": "OZtvqGyIw6mxj-R7hbeDW",
        "name": "DUTIES",
        "comment": "ON",
        "columnIds": [
          "1gDP3KCwX9PajEyfDR8cM",
          "K4jmSJUD_87o8vqn6_9Aj",
          "5BjUd-mLAKKvylR9BGDkW"
        ],
        "seqColumnIds": [
          "1gDP3KCwX9PajEyfDR8cM",
          "K4jmSJUD_87o8vqn6_9Aj",
          "5BjUd-mLAKKvylR9BGDkW"
        ],
        "ui": {
          "x": 1442,
          "y": 50,
          "zIndex": 2,
          "widthName": 60,
          "widthComment": 60,
          "color": ""
        },
        "meta": {
          "updateAt": 1736702707954,
          "createAt": 1736702707954
        }
      },
      "BNYvo6am8pGrh89TE7PeE": {
        "id": "BNYvo6am8pGrh89TE7PeE",
        "name": "EVENT_DUTIES_ASS",
        "comment": "ON",
        "columnIds": [
          "FlWqDZnzpNR15ceY0azGe",
          "yMvFNVBymrcYCQDEH__JX",
          "mwc_ZUEaAxNTBQClIG0fn",
          "ijtgaw2xa-f--5hDLbONW"
        ],
        "seqColumnIds": [
          "FlWqDZnzpNR15ceY0azGe",
          "yMvFNVBymrcYCQDEH__JX",
          "mwc_ZUEaAxNTBQClIG0fn",
          "ijtgaw2xa-f--5hDLbONW"
        ],
        "ui": {
          "x": 1060,
          "y": 258,
          "zIndex": 2,
          "widthName": 106,
          "widthComment": 60,
          "color": ""
        },
        "meta": {
          "updateAt": 1736702707955,
          "createAt": 1736702707955
        }
      },
      "FP9pvGnaKSAM2BqpEAXPU": {
        "id": "FP9pvGnaKSAM2BqpEAXPU",
        "name": "POSTS",
        "comment": "ON",
        "columnIds": [
          "IOWCZic4Gm0_K3_meiYHr",
          "L02th8K73E0Lgh86mSoFx",
          "6y_XEcVxngLsTVr6a0W4i",
          "VRBHotfED0rJ-F8df492d",
          "KNES_cQa-IiAjvUWUHs-k",
          "vFP4GcV1jL-5rIxIe695C"
        ],
        "seqColumnIds": [
          "IOWCZic4Gm0_K3_meiYHr",
          "L02th8K73E0Lgh86mSoFx",
          "6y_XEcVxngLsTVr6a0W4i",
          "VRBHotfED0rJ-F8df492d",
          "KNES_cQa-IiAjvUWUHs-k",
          "vFP4GcV1jL-5rIxIe695C"
        ],
        "ui": {
          "x": 51.7241,
          "y": 1027.7241,
          "zIndex": 2,
          "widthName": 60,
          "widthComment": 60,
          "color": ""
        },
        "meta": {
          "updateAt": 1736702754132,
          "createAt": 1736702707955
        }
      },
      "SqYiebLmcDURAb6N2ySGi": {
        "id": "SqYiebLmcDURAb6N2ySGi",
        "name": "KNOWLEDGE",
        "comment": "",
        "columnIds": [
          "Pmd4lMZ3dusQ_OwGfClQq",
          "-5O24mSs_8ImqSjB0VUIP",
          "2a3OQt8WWnL4WCseyfjwk",
          "0b6nUjVVEOP-hMpDoQtk0"
        ],
        "seqColumnIds": [
          "Pmd4lMZ3dusQ_OwGfClQq",
          "-5O24mSs_8ImqSjB0VUIP",
          "2a3OQt8WWnL4WCseyfjwk",
          "0b6nUjVVEOP-hMpDoQtk0"
        ],
        "ui": {
          "x": 50,
          "y": 490,
          "zIndex": 2,
          "widthName": 72,
          "widthComment": 60,
          "color": ""
        },
        "meta": {
          "updateAt": 1736702707955,
          "createAt": 1736702707955
        }
      },
      "PSixUObidiBMOuyFkpVx-": {
        "id": "PSixUObidiBMOuyFkpVx-",
        "name": "KNOWLEDGE_MEDIA_ASS",
        "comment": "",
        "columnIds": [
          "buTj5eCOWMiFDYUcx6L3Q",
          "wOku0Vert2tr00YvbWE9e",
          "KIxy7rhwLyrpEbziSnQKW",
          "GFSJj8RukHLiu4IIuNI96",
          "eLtP_xMEI2fH82_btjgyW"
        ],
        "seqColumnIds": [
          "buTj5eCOWMiFDYUcx6L3Q",
          "wOku0Vert2tr00YvbWE9e",
          "KIxy7rhwLyrpEbziSnQKW",
          "GFSJj8RukHLiu4IIuNI96",
          "eLtP_xMEI2fH82_btjgyW"
        ],
        "ui": {
          "x": 522,
          "y": 490,
          "zIndex": 2,
          "widthName": 139,
          "widthComment": 60,
          "color": ""
        },
        "meta": {
          "updateAt": 1736702707955,
          "createAt": 1736702707955
        }
      },
      "nYMkVPha8876Ydb9JLfWN": {
        "id": "nYMkVPha8876Ydb9JLfWN",
        "name": "MEDIA",
        "comment": "",
        "columnIds": [
          "H7XtImL3BqpVIWNl6J-Rc",
          "5TlSk2kpdl3QuiYTqEbAs",
          "aU7jJGc7hY3rTNfEjv0A9",
          "3tVvmxX4LGr0f3Cghb8MW",
          "8nJpKWjZZa2OAjWUxd1OL"
        ],
        "seqColumnIds": [
          "H7XtImL3BqpVIWNl6J-Rc",
          "5TlSk2kpdl3QuiYTqEbAs",
          "aU7jJGc7hY3rTNfEjv0A9",
          "3tVvmxX4LGr0f3Cghb8MW",
          "8nJpKWjZZa2OAjWUxd1OL"
        ],
        "ui": {
          "x": 967,
          "y": 490,
          "zIndex": 2,
          "widthName": 60,
          "widthComment": 60,
          "color": ""
        },
        "meta": {
          "updateAt": 1736702707955,
          "createAt": 1736702707955
        }
      },
      "ZD717xZ8SsmzE0VdbKCpX": {
        "id": "ZD717xZ8SsmzE0VdbKCpX",
        "name": "PERSONAL_HISTORY",
        "comment": "ON",
        "columnIds": [
          "2VuRUzikZMV5NmZ5SjYLI",
          "20IEpBfSw605VyedgdRu6",
          "3bgi4hf0Lymg0LrSlY29J",
          "olq7d54JcM9-pfnyuEjfD",
          "VFRLCkLYuc3MH3SN503mh",
          "BR4gU5CbfHp7LTF68h8R9"
        ],
        "seqColumnIds": [
          "2VuRUzikZMV5NmZ5SjYLI",
          "20IEpBfSw605VyedgdRu6",
          "3bgi4hf0Lymg0LrSlY29J",
          "olq7d54JcM9-pfnyuEjfD",
          "VFRLCkLYuc3MH3SN503mh",
          "BR4gU5CbfHp7LTF68h8R9"
        ],
        "ui": {
          "x": 691.1933,
          "y": 2946.2759,
          "zIndex": 2,
          "widthName": 111,
          "widthComment": 60,
          "color": ""
        },
        "meta": {
          "updateAt": 1736702820588,
          "createAt": 1736702707955
        }
      },
      "p0KeMVCBdrcK4MmNpbWLc": {
        "id": "p0KeMVCBdrcK4MmNpbWLc",
        "name": "REPORT_HISTORY",
        "comment": "ON",
        "columnIds": [
          "nxWRQ3uFF4R9GXteaHlqv",
          "uLurIyYTqHdPyrK2lk66H",
          "86Z8T4b70WmW1LelP0fqS",
          "qt9F3TQ07Ot8EQFHYnqFc",
          "A0ZJN0fGojyGIhR_A5qKU",
          "WthKAjDF5Br4Wrb47E96q"
        ],
        "seqColumnIds": [
          "nxWRQ3uFF4R9GXteaHlqv",
          "uLurIyYTqHdPyrK2lk66H",
          "86Z8T4b70WmW1LelP0fqS",
          "qt9F3TQ07Ot8EQFHYnqFc",
          "A0ZJN0fGojyGIhR_A5qKU",
          "WthKAjDF5Br4Wrb47E96q"
        ],
        "ui": {
          "x": 673.3679,
          "y": 3248.8094,
          "zIndex": 2,
          "widthName": 95,
          "widthComment": 60,
          "color": ""
        },
        "meta": {
          "updateAt": 1736702818051,
          "createAt": 1736702707956
        }
      },
      "SdRYuoMaQMiVi-syV-iNu": {
        "id": "SdRYuoMaQMiVi-syV-iNu",
        "name": "INTERNAL_ASSIGNS_HISTORY",
        "comment": "ON",
        "columnIds": [
          "awtTXq63QYzGVq2jUe6Hc",
          "lhEwzoXcgOL84TcjnGUze",
          "ztY8UuGKH_RwjZv6SBKQV",
          "16p46SJ5NllCORM8Q9zEw",
          "XPiBBVN14JF8FPMEpplmb",
          "I9gspjYcfIm-jsNp1Q6Nh"
        ],
        "seqColumnIds": [
          "awtTXq63QYzGVq2jUe6Hc",
          "lhEwzoXcgOL84TcjnGUze",
          "ztY8UuGKH_RwjZv6SBKQV",
          "16p46SJ5NllCORM8Q9zEw",
          "XPiBBVN14JF8FPMEpplmb",
          "I9gspjYcfIm-jsNp1Q6Nh"
        ],
        "ui": {
          "x": 85.0197,
          "y": 3240.4261,
          "zIndex": 2,
          "widthName": 160,
          "widthComment": 60,
          "color": ""
        },
        "meta": {
          "updateAt": 1736702815620,
          "createAt": 1736702707956
        }
      },
      "PFV4tkpKUrgv3L36oIFpE": {
        "id": "PFV4tkpKUrgv3L36oIFpE",
        "name": "PUBLIC_ACTIVITIES_HISTORY",
        "comment": "ON",
        "columnIds": [
          "qKuJI7UA9_ihsMo4t5S1v",
          "g1rwiOXt0w72YMkqq-HHd",
          "BSzM84CZcFOJAaErM5RET",
          "eoz9pYj0kfTXNHdqgF8ZR",
          "Kt9YjqnKAS6aUKMoKlSDa",
          "3dIHwknTbE-87xtJGfmhX"
        ],
        "seqColumnIds": [
          "qKuJI7UA9_ihsMo4t5S1v",
          "g1rwiOXt0w72YMkqq-HHd",
          "BSzM84CZcFOJAaErM5RET",
          "eoz9pYj0kfTXNHdqgF8ZR",
          "Kt9YjqnKAS6aUKMoKlSDa",
          "3dIHwknTbE-87xtJGfmhX"
        ],
        "ui": {
          "x": 94.2839,
          "y": 2948.062,
          "zIndex": 2,
          "widthName": 154,
          "widthComment": 60,
          "color": ""
        },
        "meta": {
          "updateAt": 1736702816716,
          "createAt": 1736702707956
        }
      }
    },
    "tableColumnEntities": {
      "BhinAjCHkM-EZJ2qpB14B": {
        "id": "BhinAjCHkM-EZJ2qpB14B",
        "tableId": "cQpUxLpOYUyxPH0YoHluk",
        "name": "MEMBER_ID",
        "comment": "",
        "dataType": "NUMBER",
        "default": "",
        "options": 2,
        "ui": {
          "keys": 1,
          "widthName": 66,
          "widthComment": 60,
          "widthDataType": 60,
          "widthDefault": 60
        },
        "meta": {
          "updateAt": 1736702707952,
          "createAt": 1736702707952
        }
      },
      "ujRb3EvYOYxMco1d_BGya": {
        "id": "ujRb3EvYOYxMco1d_BGya",
        "tableId": "cQpUxLpOYUyxPH0YoHluk",
        "name": "FIRST_NAME",
        "comment": "",
        "dataType": "VARCHAR2(40)",
        "default": "",
        "options": 12,
        "ui": {
          "keys": 0,
          "widthName": 69,
          "widthComment": 60,
          "widthDataType": 81,
          "widthDefault": 60
        },
        "meta": {
          "updateAt": 1736702707952,
          "createAt": 1736702707952
        }
      },
      "NlxNnsXhyui5UGSYZ31IV": {
        "id": "NlxNnsXhyui5UGSYZ31IV",
        "tableId": "cQpUxLpOYUyxPH0YoHluk",
        "name": "LAST_NAME",
        "comment": "",
        "dataType": "VARCHAR2(80)",
        "default": "",
        "options": 12,
        "ui": {
          "keys": 0,
          "widthName": 67,
          "widthComment": 60,
          "widthDataType": 81,
          "widthDefault": 60
        },
        "meta": {
          "updateAt": 1736702707952,
          "createAt": 1736702707952
        }
      },
      "zkYpoxxY_wQ8oFXe7QxcM": {
        "id": "zkYpoxxY_wQ8oFXe7QxcM",
        "tableId": "cQpUxLpOYUyxPH0YoHluk",
        "name": "MOTHERS_NAME",
        "comment": "",
        "dataType": "VARCHAR2(120)",
        "default": "",
        "options": 12,
        "ui": {
          "keys": 0,
          "widthName": 94,
          "widthComment": 60,
          "widthDataType": 87,
          "widthDefault": 60
        },
        "meta": {
          "updateAt": 1736702707952,
          "createAt": 1736702707952
        }
      },
      "gQDwcYL8XdTr4DbT3JEND": {
        "id": "gQDwcYL8XdTr4DbT3JEND",
        "tableId": "cQpUxLpOYUyxPH0YoHluk",
        "name": "MOTHERS_TELEPHONE_NUMBER",
        "comment": "",
        "dataType": "VARCHAR2(12)",
        "default": "",
        "options": 12,
        "ui": {
          "keys": 0,
          "widthName": 177,
          "widthComment": 60,
          "widthDataType": 81,
          "widthDefault": 60
        },
        "meta": {
          "updateAt": 1736702707952,
          "createAt": 1736702707952
        }
      },
      "xBnMXdsxV3BPD78boihEv": {
        "id": "xBnMXdsxV3BPD78boihEv",
        "tableId": "cQpUxLpOYUyxPH0YoHluk",
        "name": "MOTHERS_EMAIL",
        "comment": "",
        "dataType": "VARCHAR2(60)",
        "default": "",
        "options": 12,
        "ui": {
          "keys": 0,
          "widthName": 94,
          "widthComment": 60,
          "widthDataType": 81,
          "widthDefault": 60
        },
        "meta": {
          "updateAt": 1736702707952,
          "createAt": 1736702707952
        }
      },
      "JU0tX1DQuSvC3wPz-sGEN": {
        "id": "JU0tX1DQuSvC3wPz-sGEN",
        "tableId": "cQpUxLpOYUyxPH0YoHluk",
        "name": "MEMBER_EMAIL",
        "comment": "",
        "dataType": "VARCHAR2(60)",
        "default": "",
        "options": 4,
        "ui": {
          "keys": 0,
          "widthName": 88,
          "widthComment": 60,
          "widthDataType": 81,
          "widthDefault": 60
        },
        "meta": {
          "updateAt": 1736702707952,
          "createAt": 1736702707952
        }
      },
      "qaKwZqUa27TkL3CdEtqji": {
        "id": "qaKwZqUa27TkL3CdEtqji",
        "tableId": "cQpUxLpOYUyxPH0YoHluk",
        "name": "MEMBER_TELEPHONE_NUMBER",
        "comment": "",
        "dataType": "VARCHAR2(12)",
        "default": "",
        "options": 4,
        "ui": {
          "keys": 0,
          "widthName": 171,
          "widthComment": 60,
          "widthDataType": 81,
          "widthDefault": 60
        },
        "meta": {
          "updateAt": 1736702707952,
          "createAt": 1736702707952
        }
      },
      "UPXj8Y9-_oBgBOqixds_G": {
        "id": "UPXj8Y9-_oBgBOqixds_G",
        "tableId": "cQpUxLpOYUyxPH0YoHluk",
        "name": "BIRTH_DATE",
        "comment": "",
        "dataType": "DATE",
        "default": "",
        "options": 0,
        "ui": {
          "keys": 0,
          "widthName": 66,
          "widthComment": 60,
          "widthDataType": 60,
          "widthDefault": 60
        },
        "meta": {
          "updateAt": 1736702707953,
          "createAt": 1736702707953
        }
      },
      "3ia5CK-15TX_ZMuSzNdob": {
        "id": "3ia5CK-15TX_ZMuSzNdob",
        "tableId": "cQpUxLpOYUyxPH0YoHluk",
        "name": "ORS_ID",
        "comment": "",
        "dataType": "NUMBER",
        "default": "",
        "options": 0,
        "ui": {
          "keys": 2,
          "widthName": 60,
          "widthComment": 60,
          "widthDataType": 60,
          "widthDefault": 60
        },
        "meta": {
          "updateAt": 1736702707953,
          "createAt": 1736702707953
        }
      },
      "-tslz2qAlyGvJJWyH6mXH": {
        "id": "-tslz2qAlyGvJJWyH6mXH",
        "tableId": "cQpUxLpOYUyxPH0YoHluk",
        "name": "PATROL_ID",
        "comment": "",
        "dataType": "NUMBER",
        "default": "",
        "options": 0,
        "ui": {
          "keys": 2,
          "widthName": 60,
          "widthComment": 60,
          "widthDataType": 60,
          "widthDefault": 60
        },
        "meta": {
          "updateAt": 1736702707953,
          "createAt": 1736702707953
        }
      },
      "pIDdVjOp3mnUcXmR68tPu": {
        "id": "pIDdVjOp3mnUcXmR68tPu",
        "tableId": "_DQoyIW0mWh4yxWzDoo-q",
        "name": "ADDRESS_ID",
        "comment": "",
        "dataType": "NUMBER",
        "default": "",
        "options": 2,
        "ui": {
          "keys": 1,
          "widthName": 69,
          "widthComment": 60,
          "widthDataType": 60,
          "widthDefault": 60
        },
        "meta": {
          "updateAt": 1736702707953,
          "createAt": 1736702707953
        }
      },
      "pv0TbeBEKpqzYNIwXJeIT": {
        "id": "pv0TbeBEKpqzYNIwXJeIT",
        "tableId": "_DQoyIW0mWh4yxWzDoo-q",
        "name": "ZIP_CODE",
        "comment": "",
        "dataType": "VARCHAR2(10)",
        "default": "",
        "options": 8,
        "ui": {
          "keys": 0,
          "widthName": 60,
          "widthComment": 60,
          "widthDataType": 81,
          "widthDefault": 60
        },
        "meta": {
          "updateAt": 1736702707953,
          "createAt": 1736702707953
        }
      },
      "q4wwx60Dnz3GLv7SIIG1k": {
        "id": "q4wwx60Dnz3GLv7SIIG1k",
        "tableId": "_DQoyIW0mWh4yxWzDoo-q",
        "name": "COUNTRY",
        "comment": "",
        "dataType": "VARCHAR2(50)",
        "default": "",
        "options": 8,
        "ui": {
          "keys": 0,
          "widthName": 60,
          "widthComment": 60,
          "widthDataType": 81,
          "widthDefault": 60
        },
        "meta": {
          "updateAt": 1736702707953,
          "createAt": 1736702707953
        }
      },
      "6yeij-QjJmRubLk-SxQXe": {
        "id": "6yeij-QjJmRubLk-SxQXe",
        "tableId": "_DQoyIW0mWh4yxWzDoo-q",
        "name": "CITY",
        "comment": "",
        "dataType": "VARCHAR2(50)",
        "default": "",
        "options": 8,
        "ui": {
          "keys": 0,
          "widthName": 60,
          "widthComment": 60,
          "widthDataType": 81,
          "widthDefault": 60
        },
        "meta": {
          "updateAt": 1736702707953,
          "createAt": 1736702707953
        }
      },
      "nYGBxDGn0ERdfDkAKJO5R": {
        "id": "nYGBxDGn0ERdfDkAKJO5R",
        "tableId": "_DQoyIW0mWh4yxWzDoo-q",
        "name": "STREET_NAME",
        "comment": "",
        "dataType": "VARCHAR2(100)",
        "default": "",
        "options": 8,
        "ui": {
          "keys": 0,
          "widthName": 79,
          "widthComment": 60,
          "widthDataType": 87,
          "widthDefault": 60
        },
        "meta": {
          "updateAt": 1736702707953,
          "createAt": 1736702707953
        }
      },
      "mDrP6teVkoodXGBiHfJUe": {
        "id": "mDrP6teVkoodXGBiHfJUe",
        "tableId": "_DQoyIW0mWh4yxWzDoo-q",
        "name": "STREET_TYPE",
        "comment": "",
        "dataType": "VARCHAR2(40)",
        "default": "",
        "options": 8,
        "ui": {
          "keys": 0,
          "widthName": 71,
          "widthComment": 60,
          "widthDataType": 81,
          "widthDefault": 60
        },
        "meta": {
          "updateAt": 1736702707953,
          "createAt": 1736702707953
        }
      },
      "vC-djrn-FRk9OyQjMaCns": {
        "id": "vC-djrn-FRk9OyQjMaCns",
        "tableId": "_DQoyIW0mWh4yxWzDoo-q",
        "name": "HOUSE_NUMBER",
        "comment": "",
        "dataType": "VARCHAR2(30)",
        "default": "",
        "options": 8,
        "ui": {
          "keys": 0,
          "widthName": 93,
          "widthComment": 60,
          "widthDataType": 81,
          "widthDefault": 60
        },
        "meta": {
          "updateAt": 1736702707953,
          "createAt": 1736702707953
        }
      },
      "wXT3fJXmzZ8jO7z7W_9LD": {
        "id": "wXT3fJXmzZ8jO7z7W_9LD",
        "tableId": "_DQoyIW0mWh4yxWzDoo-q",
        "name": "CHECK",
        "comment": "",
        "dataType": "",
        "default": "",
        "options": 0,
        "ui": {
          "keys": 0,
          "widthName": 60,
          "widthComment": 60,
          "widthDataType": 60,
          "widthDefault": 60
        },
        "meta": {
          "updateAt": 1736702707953,
          "createAt": 1736702707953
        }
      },
      "_UZYBkq119OtyC2Li4acS": {
        "id": "_UZYBkq119OtyC2Li4acS",
        "tableId": "8EodW7KK530D9bHNIN4vC",
        "name": "ADDRESS_ID",
        "comment": "",
        "dataType": "NUMBER",
        "default": "",
        "options": 10,
        "ui": {
          "keys": 3,
          "widthName": 69,
          "widthComment": 60,
          "widthDataType": 60,
          "widthDefault": 60
        },
        "meta": {
          "updateAt": 1736702707953,
          "createAt": 1736702707953
        }
      },
      "XvmTxiDYWd8reNv6JBG1f": {
        "id": "XvmTxiDYWd8reNv6JBG1f",
        "tableId": "8EodW7KK530D9bHNIN4vC",
        "name": "MEMBER_ID",
        "comment": "",
        "dataType": "NUMBER",
        "default": "",
        "options": 10,
        "ui": {
          "keys": 3,
          "widthName": 66,
          "widthComment": 60,
          "widthDataType": 60,
          "widthDefault": 60
        },
        "meta": {
          "updateAt": 1736702707953,
          "createAt": 1736702707953
        }
      },
      "53WTCJSUe_-B_Zd4R5Dp_": {
        "id": "53WTCJSUe_-B_Zd4R5Dp_",
        "tableId": "ZlJvFqugz39C-zOVp8Niy",
        "name": "STATUS_ID",
        "comment": "",
        "dataType": "NUMBER",
        "default": "",
        "options": 2,
        "ui": {
          "keys": 1,
          "widthName": 60,
          "widthComment": 60,
          "widthDataType": 60,
          "widthDefault": 60
        },
        "meta": {
          "updateAt": 1736702707953,
          "createAt": 1736702707953
        }
      },
      "Jds6IawjmIAeVJtD3Em2e": {
        "id": "Jds6IawjmIAeVJtD3Em2e",
        "tableId": "ZlJvFqugz39C-zOVp8Niy",
        "name": "MEMBER_ID",
        "comment": "",
        "dataType": "NUMBER",
        "default": "",
        "options": 12,
        "ui": {
          "keys": 2,
          "widthName": 66,
          "widthComment": 60,
          "widthDataType": 60,
          "widthDefault": 60
        },
        "meta": {
          "updateAt": 1736702707953,
          "createAt": 1736702707953
        }
      },
      "DXbgnQEp-hjITzq8OAef2": {
        "id": "DXbgnQEp-hjITzq8OAef2",
        "tableId": "ZlJvFqugz39C-zOVp8Niy",
        "name": "RANK_ID",
        "comment": "",
        "dataType": "NUMBER",
        "default": "",
        "options": 12,
        "ui": {
          "keys": 0,
          "widthName": 60,
          "widthComment": 60,
          "widthDataType": 60,
          "widthDefault": 60
        },
        "meta": {
          "updateAt": 1736702707953,
          "createAt": 1736702707953
        }
      },
      "eHLX5mnuaVt0UK-qfQAOw": {
        "id": "eHLX5mnuaVt0UK-qfQAOw",
        "tableId": "ZlJvFqugz39C-zOVp8Niy",
        "name": "PROMOTION_TIME_END",
        "comment": "",
        "dataType": "YEAR",
        "default": "SYSTIMESTAMP",
        "options": 0,
        "ui": {
          "keys": 0,
          "widthName": 131,
          "widthComment": 60,
          "widthDataType": 60,
          "widthDefault": 85
        },
        "meta": {
          "updateAt": 1736702707953,
          "createAt": 1736702707953
        }
      },
      "tp3ydmosVp2zAr3aq-mZe": {
        "id": "tp3ydmosVp2zAr3aq-mZe",
        "tableId": "QJEdFeKsrm8oSCMS_Se_k",
        "name": "ORS_ID",
        "comment": "",
        "dataType": "NUMBER",
        "default": "",
        "options": 2,
        "ui": {
          "keys": 1,
          "widthName": 60,
          "widthComment": 60,
          "widthDataType": 60,
          "widthDefault": 60
        },
        "meta": {
          "updateAt": 1736702707953,
          "createAt": 1736702707953
        }
      },
      "iLrKWVUHb3U2UaOYC1KwL": {
        "id": "iLrKWVUHb3U2UaOYC1KwL",
        "tableId": "QJEdFeKsrm8oSCMS_Se_k",
        "name": "ORS_NAME",
        "comment": "",
        "dataType": "VARCHAR(100)",
        "default": "",
        "options": 12,
        "ui": {
          "keys": 0,
          "widthName": 63,
          "widthComment": 60,
          "widthDataType": 81,
          "widthDefault": 60
        },
        "meta": {
          "updateAt": 1736702707954,
          "createAt": 1736702707954
        }
      },
      "6rs_DKqDGC78tVUBATcQ0": {
        "id": "6rs_DKqDGC78tVUBATcQ0",
        "tableId": "QJEdFeKsrm8oSCMS_Se_k",
        "name": "PATROL_ID",
        "comment": "",
        "dataType": "NUMBER",
        "default": "",
        "options": 8,
        "ui": {
          "keys": 2,
          "widthName": 60,
          "widthComment": 60,
          "widthDataType": 60,
          "widthDefault": 60
        },
        "meta": {
          "updateAt": 1736702707954,
          "createAt": 1736702707954
        }
      },
      "5kxByovBBYWdD-K23zLAq": {
        "id": "5kxByovBBYWdD-K23zLAq",
        "tableId": "QJEdFeKsrm8oSCMS_Se_k",
        "name": "LEADER_ID",
        "comment": "",
        "dataType": "NUMBER",
        "default": "",
        "options": 0,
        "ui": {
          "keys": 2,
          "widthName": 60,
          "widthComment": 60,
          "widthDataType": 60,
          "widthDefault": 60
        },
        "meta": {
          "updateAt": 1736702707954,
          "createAt": 1736702707954
        }
      },
      "jGU9HI-YFyQ9eNhgb1SdC": {
        "id": "jGU9HI-YFyQ9eNhgb1SdC",
        "tableId": "cQTtce6Cto28iUz5GpSII",
        "name": "PATROL_ID",
        "comment": "",
        "dataType": "NUMBER",
        "default": "",
        "options": 2,
        "ui": {
          "keys": 1,
          "widthName": 60,
          "widthComment": 60,
          "widthDataType": 60,
          "widthDefault": 60
        },
        "meta": {
          "updateAt": 1736702707954,
          "createAt": 1736702707954
        }
      },
      "PLrSDDg8rE93d4UUU7KdC": {
        "id": "PLrSDDg8rE93d4UUU7KdC",
        "tableId": "cQTtce6Cto28iUz5GpSII",
        "name": "PATROL_NAME",
        "comment": "",
        "dataType": "VARCHAR2(100)",
        "default": "",
        "options": 12,
        "ui": {
          "keys": 0,
          "widthName": 81,
          "widthComment": 60,
          "widthDataType": 87,
          "widthDefault": 60
        },
        "meta": {
          "updateAt": 1736702707954,
          "createAt": 1736702707954
        }
      },
      "XRdIym3dC9bVp7iovgy19": {
        "id": "XRdIym3dC9bVp7iovgy19",
        "tableId": "cQTtce6Cto28iUz5GpSII",
        "name": "LEADER_ID",
        "comment": "",
        "dataType": "NUMBER",
        "default": "",
        "options": 0,
        "ui": {
          "keys": 2,
          "widthName": 60,
          "widthComment": 60,
          "widthDataType": 60,
          "widthDefault": 60
        },
        "meta": {
          "updateAt": 1736702707954,
          "createAt": 1736702707954
        }
      },
      "D3vHPrhI4epynrutXEsb4": {
        "id": "D3vHPrhI4epynrutXEsb4",
        "tableId": "i1fNivitx70K1rJyaTswC",
        "name": "MEETING_ID",
        "comment": "",
        "dataType": "NUMBER",
        "default": "",
        "options": 2,
        "ui": {
          "keys": 1,
          "widthName": 68,
          "widthComment": 60,
          "widthDataType": 60,
          "widthDefault": 60
        },
        "meta": {
          "updateAt": 1736702707954,
          "createAt": 1736702707954
        }
      },
      "61-sqQLNZyBzj3qyPAqQ1": {
        "id": "61-sqQLNZyBzj3qyPAqQ1",
        "tableId": "i1fNivitx70K1rJyaTswC",
        "name": "MEETING_CONTENT",
        "comment": "",
        "dataType": "CLOB",
        "default": "",
        "options": 8,
        "ui": {
          "keys": 0,
          "widthName": 109,
          "widthComment": 60,
          "widthDataType": 60,
          "widthDefault": 60
        },
        "meta": {
          "updateAt": 1736702707954,
          "createAt": 1736702707954
        }
      },
      "m6eIJyLVOZV0CvjNu8HYN": {
        "id": "m6eIJyLVOZV0CvjNu8HYN",
        "tableId": "i1fNivitx70K1rJyaTswC",
        "name": "AUTHOR_ID",
        "comment": "",
        "dataType": "NUMBER",
        "default": "",
        "options": 8,
        "ui": {
          "keys": 2,
          "widthName": 65,
          "widthComment": 60,
          "widthDataType": 60,
          "widthDefault": 60
        },
        "meta": {
          "updateAt": 1736702707954,
          "createAt": 1736702707954
        }
      },
      "Lzcu_RWaPnSpqReq4cY-m": {
        "id": "Lzcu_RWaPnSpqReq4cY-m",
        "tableId": "i1fNivitx70K1rJyaTswC",
        "name": "EVENT_ID",
        "comment": "",
        "dataType": "NUMBER",
        "default": "",
        "options": 8,
        "ui": {
          "keys": 2,
          "widthName": 60,
          "widthComment": 60,
          "widthDataType": 60,
          "widthDefault": 60
        },
        "meta": {
          "updateAt": 1736702707954,
          "createAt": 1736702707954
        }
      },
      "4pIstWXyGtnIEAoAYohBA": {
        "id": "4pIstWXyGtnIEAoAYohBA",
        "tableId": "i1fNivitx70K1rJyaTswC",
        "name": "CREATED_AT",
        "comment": "",
        "dataType": "TIMESTAMP",
        "default": "CURRENT_TIMESTAMP",
        "options": 0,
        "ui": {
          "keys": 0,
          "widthName": 68,
          "widthComment": 60,
          "widthDataType": 65,
          "widthDefault": 122
        },
        "meta": {
          "updateAt": 1736702707954,
          "createAt": 1736702707954
        }
      },
      "mIj384ymoiJVYzINDjrsU": {
        "id": "mIj384ymoiJVYzINDjrsU",
        "tableId": "i1fNivitx70K1rJyaTswC",
        "name": "MODIFIED_AT",
        "comment": "",
        "dataType": "TIMESTAMP",
        "default": "CURRENT_TIMESTAMP",
        "options": 0,
        "ui": {
          "keys": 0,
          "widthName": 75,
          "widthComment": 60,
          "widthDataType": 65,
          "widthDefault": 122
        },
        "meta": {
          "updateAt": 1736702707954,
          "createAt": 1736702707954
        }
      },
      "5qrz9OylEkRFN2lzLGIMt": {
        "id": "5qrz9OylEkRFN2lzLGIMt",
        "tableId": "C0RjPc1YqTUs69VpM8yqs",
        "name": "REPORT_ID",
        "comment": "",
        "dataType": "NUMBER",
        "default": "",
        "options": 2,
        "ui": {
          "keys": 1,
          "widthName": 61,
          "widthComment": 60,
          "widthDataType": 60,
          "widthDefault": 60
        },
        "meta": {
          "updateAt": 1736702707954,
          "createAt": 1736702707954
        }
      },
      "pug3YHd23o0zInC9m4nT3": {
        "id": "pug3YHd23o0zInC9m4nT3",
        "tableId": "C0RjPc1YqTUs69VpM8yqs",
        "name": "REPORT_CONTENT",
        "comment": "",
        "dataType": "CLOB",
        "default": "",
        "options": 8,
        "ui": {
          "keys": 0,
          "widthName": 102,
          "widthComment": 60,
          "widthDataType": 60,
          "widthDefault": 60
        },
        "meta": {
          "updateAt": 1736702707954,
          "createAt": 1736702707954
        }
      },
      "pyc8UEooyewc6SbjmsJSQ": {
        "id": "pyc8UEooyewc6SbjmsJSQ",
        "tableId": "C0RjPc1YqTUs69VpM8yqs",
        "name": "AUTHOR_ID",
        "comment": "",
        "dataType": "NUMBER",
        "default": "",
        "options": 8,
        "ui": {
          "keys": 2,
          "widthName": 65,
          "widthComment": 60,
          "widthDataType": 60,
          "widthDefault": 60
        },
        "meta": {
          "updateAt": 1736702707954,
          "createAt": 1736702707954
        }
      },
      "JQYN-i48j14DjN2aLyhVF": {
        "id": "JQYN-i48j14DjN2aLyhVF",
        "tableId": "C0RjPc1YqTUs69VpM8yqs",
        "name": "ORS_ID",
        "comment": "",
        "dataType": "NUMBER",
        "default": "",
        "options": 8,
        "ui": {
          "keys": 2,
          "widthName": 60,
          "widthComment": 60,
          "widthDataType": 60,
          "widthDefault": 60
        },
        "meta": {
          "updateAt": 1736702707954,
          "createAt": 1736702707954
        }
      },
      "TFZGWRB2fNfJvCpu7yq62": {
        "id": "TFZGWRB2fNfJvCpu7yq62",
        "tableId": "C0RjPc1YqTUs69VpM8yqs",
        "name": "CREATED_AT",
        "comment": "",
        "dataType": "TIMESTAMP",
        "default": "CURRENT_TIMESTAMP",
        "options": 0,
        "ui": {
          "keys": 0,
          "widthName": 68,
          "widthComment": 60,
          "widthDataType": 65,
          "widthDefault": 122
        },
        "meta": {
          "updateAt": 1736702707954,
          "createAt": 1736702707954
        }
      },
      "MRSE6r5H43vr24b5q1pNl": {
        "id": "MRSE6r5H43vr24b5q1pNl",
        "tableId": "C0RjPc1YqTUs69VpM8yqs",
        "name": "MODIFIED_AT",
        "comment": "",
        "dataType": "TIMESTAMP",
        "default": "CURRENT_TIMESTAMP",
        "options": 0,
        "ui": {
          "keys": 0,
          "widthName": 75,
          "widthComment": 60,
          "widthDataType": 65,
          "widthDefault": 122
        },
        "meta": {
          "updateAt": 1736702707954,
          "createAt": 1736702707954
        }
      },
      "-Dib_cMyUHkBlVZpEQhdj": {
        "id": "-Dib_cMyUHkBlVZpEQhdj",
        "tableId": "4f9Z8zFWxVX8rBoWBLdhW",
        "name": "EVENT_ID",
        "comment": "",
        "dataType": "NUMBER",
        "default": "",
        "options": 2,
        "ui": {
          "keys": 1,
          "widthName": 60,
          "widthComment": 60,
          "widthDataType": 60,
          "widthDefault": 60
        },
        "meta": {
          "updateAt": 1736702707954,
          "createAt": 1736702707954
        }
      },
      "JeHFLXSbxkJZt3tjiJhXn": {
        "id": "JeHFLXSbxkJZt3tjiJhXn",
        "tableId": "4f9Z8zFWxVX8rBoWBLdhW",
        "name": "EVENT_NAME",
        "comment": "",
        "dataType": "VARCHAR2(100)",
        "default": "",
        "options": 8,
        "ui": {
          "keys": 0,
          "widthName": 75,
          "widthComment": 60,
          "widthDataType": 87,
          "widthDefault": 60
        },
        "meta": {
          "updateAt": 1736702707954,
          "createAt": 1736702707954
        }
      },
      "kQ32JA5h52__SNrgXvfUN": {
        "id": "kQ32JA5h52__SNrgXvfUN",
        "tableId": "4f9Z8zFWxVX8rBoWBLdhW",
        "name": "EVENT_DESCRIPTION",
        "comment": "",
        "dataType": "VARCHAR2(2000)",
        "default": "",
        "options": 0,
        "ui": {
          "keys": 0,
          "widthName": 115,
          "widthComment": 60,
          "widthDataType": 94,
          "widthDefault": 60
        },
        "meta": {
          "updateAt": 1736702707954,
          "createAt": 1736702707954
        }
      },
      "-jTVx9Bs0kqh0Ky9HIWLO": {
        "id": "-jTVx9Bs0kqh0Ky9HIWLO",
        "tableId": "4f9Z8zFWxVX8rBoWBLdhW",
        "name": "DATE_START",
        "comment": "",
        "dataType": "TIMESTAMP",
        "default": "",
        "options": 8,
        "ui": {
          "keys": 0,
          "widthName": 67,
          "widthComment": 60,
          "widthDataType": 65,
          "widthDefault": 60
        },
        "meta": {
          "updateAt": 1736702707954,
          "createAt": 1736702707954
        }
      },
      "nF4f_oQyPaBM32uzGKVHV": {
        "id": "nF4f_oQyPaBM32uzGKVHV",
        "tableId": "4f9Z8zFWxVX8rBoWBLdhW",
        "name": "DATE_END",
        "comment": "",
        "dataType": "TIMESTAMP",
        "default": "",
        "options": 8,
        "ui": {
          "keys": 0,
          "widthName": 60,
          "widthComment": 60,
          "widthDataType": 65,
          "widthDefault": 60
        },
        "meta": {
          "updateAt": 1736702707954,
          "createAt": 1736702707954
        }
      },
      "SQ-cv5LxbPDagqOlPhVjj": {
        "id": "SQ-cv5LxbPDagqOlPhVjj",
        "tableId": "4f9Z8zFWxVX8rBoWBLdhW",
        "name": "CHECK",
        "comment": "",
        "dataType": "",
        "default": "",
        "options": 0,
        "ui": {
          "keys": 0,
          "widthName": 60,
          "widthComment": 60,
          "widthDataType": 60,
          "widthDefault": 60
        },
        "meta": {
          "updateAt": 1736702707954,
          "createAt": 1736702707954
        }
      },
      "1gDP3KCwX9PajEyfDR8cM": {
        "id": "1gDP3KCwX9PajEyfDR8cM",
        "tableId": "OZtvqGyIw6mxj-R7hbeDW",
        "name": "DUTY_ID",
        "comment": "",
        "dataType": "NUMBER",
        "default": "",
        "options": 2,
        "ui": {
          "keys": 1,
          "widthName": 60,
          "widthComment": 60,
          "widthDataType": 60,
          "widthDefault": 60
        },
        "meta": {
          "updateAt": 1736702707955,
          "createAt": 1736702707955
        }
      },
      "K4jmSJUD_87o8vqn6_9Aj": {
        "id": "K4jmSJUD_87o8vqn6_9Aj",
        "tableId": "OZtvqGyIw6mxj-R7hbeDW",
        "name": "DUTY_NAME",
        "comment": "",
        "dataType": "VARCHAR2(100)",
        "default": "",
        "options": 8,
        "ui": {
          "keys": 0,
          "widthName": 70,
          "widthComment": 60,
          "widthDataType": 87,
          "widthDefault": 60
        },
        "meta": {
          "updateAt": 1736702707955,
          "createAt": 1736702707955
        }
      },
      "5BjUd-mLAKKvylR9BGDkW": {
        "id": "5BjUd-mLAKKvylR9BGDkW",
        "tableId": "OZtvqGyIw6mxj-R7hbeDW",
        "name": "DUTY_DESCRIPTION",
        "comment": "",
        "dataType": "VARCHAR2(500)",
        "default": "",
        "options": 0,
        "ui": {
          "keys": 0,
          "widthName": 110,
          "widthComment": 60,
          "widthDataType": 87,
          "widthDefault": 60
        },
        "meta": {
          "updateAt": 1736702707955,
          "createAt": 1736702707955
        }
      },
      "FlWqDZnzpNR15ceY0azGe": {
        "id": "FlWqDZnzpNR15ceY0azGe",
        "tableId": "BNYvo6am8pGrh89TE7PeE",
        "name": "EVENT_ID",
        "comment": "",
        "dataType": "NUMBER",
        "default": "",
        "options": 10,
        "ui": {
          "keys": 3,
          "widthName": 60,
          "widthComment": 60,
          "widthDataType": 60,
          "widthDefault": 60
        },
        "meta": {
          "updateAt": 1736702707955,
          "createAt": 1736702707955
        }
      },
      "yMvFNVBymrcYCQDEH__JX": {
        "id": "yMvFNVBymrcYCQDEH__JX",
        "tableId": "BNYvo6am8pGrh89TE7PeE",
        "name": "DUTY_ID",
        "comment": "",
        "dataType": "NUMBER",
        "default": "",
        "options": 10,
        "ui": {
          "keys": 3,
          "widthName": 60,
          "widthComment": 60,
          "widthDataType": 60,
          "widthDefault": 60
        },
        "meta": {
          "updateAt": 1736702707955,
          "createAt": 1736702707955
        }
      },
      "mwc_ZUEaAxNTBQClIG0fn": {
        "id": "mwc_ZUEaAxNTBQClIG0fn",
        "tableId": "BNYvo6am8pGrh89TE7PeE",
        "name": "MEMBER_ID",
        "comment": "",
        "dataType": "NUMBER",
        "default": "",
        "options": 10,
        "ui": {
          "keys": 3,
          "widthName": 66,
          "widthComment": 60,
          "widthDataType": 60,
          "widthDefault": 60
        },
        "meta": {
          "updateAt": 1736702707955,
          "createAt": 1736702707955
        }
      },
      "ijtgaw2xa-f--5hDLbONW": {
        "id": "ijtgaw2xa-f--5hDLbONW",
        "tableId": "BNYvo6am8pGrh89TE7PeE",
        "name": "ASSIGNMENT_END_DATE",
        "comment": "",
        "dataType": "TIMESTAMP",
        "default": "ADD_MONTHS",
        "options": 0,
        "ui": {
          "keys": 0,
          "widthName": 136,
          "widthComment": 60,
          "widthDataType": 65,
          "widthDefault": 82
        },
        "meta": {
          "updateAt": 1736702707955,
          "createAt": 1736702707955
        }
      },
      "IOWCZic4Gm0_K3_meiYHr": {
        "id": "IOWCZic4Gm0_K3_meiYHr",
        "tableId": "FP9pvGnaKSAM2BqpEAXPU",
        "name": "POST_ID",
        "comment": "",
        "dataType": "NUMBER",
        "default": "",
        "options": 2,
        "ui": {
          "keys": 1,
          "widthName": 60,
          "widthComment": 60,
          "widthDataType": 60,
          "widthDefault": 60
        },
        "meta": {
          "updateAt": 1736702707955,
          "createAt": 1736702707955
        }
      },
      "L02th8K73E0Lgh86mSoFx": {
        "id": "L02th8K73E0Lgh86mSoFx",
        "tableId": "FP9pvGnaKSAM2BqpEAXPU",
        "name": "POST_NAME",
        "comment": "",
        "dataType": "VARCHAR2(100)",
        "default": "",
        "options": 8,
        "ui": {
          "keys": 0,
          "widthName": 69,
          "widthComment": 60,
          "widthDataType": 87,
          "widthDefault": 60
        },
        "meta": {
          "updateAt": 1736702707955,
          "createAt": 1736702707955
        }
      },
      "6y_XEcVxngLsTVr6a0W4i": {
        "id": "6y_XEcVxngLsTVr6a0W4i",
        "tableId": "FP9pvGnaKSAM2BqpEAXPU",
        "name": "POST_DESCRIPTION",
        "comment": "",
        "dataType": "VARCHAR2(2000)",
        "default": "",
        "options": 0,
        "ui": {
          "keys": 0,
          "widthName": 108,
          "widthComment": 60,
          "widthDataType": 94,
          "widthDefault": 60
        },
        "meta": {
          "updateAt": 1736702707955,
          "createAt": 1736702707955
        }
      },
      "VRBHotfED0rJ-F8df492d": {
        "id": "VRBHotfED0rJ-F8df492d",
        "tableId": "FP9pvGnaKSAM2BqpEAXPU",
        "name": "POST_TYPE",
        "comment": "",
        "dataType": "VARCHAR2(4)",
        "default": "",
        "options": 8,
        "ui": {
          "keys": 0,
          "widthName": 61,
          "widthComment": 60,
          "widthDataType": 75,
          "widthDefault": 60
        },
        "meta": {
          "updateAt": 1736702707955,
          "createAt": 1736702707955
        }
      },
      "KNES_cQa-IiAjvUWUHs-k": {
        "id": "KNES_cQa-IiAjvUWUHs-k",
        "tableId": "FP9pvGnaKSAM2BqpEAXPU",
        "name": "BLOG",
        "comment": "",
        "dataType": "",
        "default": "",
        "options": 0,
        "ui": {
          "keys": 0,
          "widthName": 60,
          "widthComment": 60,
          "widthDataType": 60,
          "widthDefault": 60
        },
        "meta": {
          "updateAt": 1736702707955,
          "createAt": 1736702707955
        }
      },
      "vFP4GcV1jL-5rIxIe695C": {
        "id": "vFP4GcV1jL-5rIxIe695C",
        "tableId": "FP9pvGnaKSAM2BqpEAXPU",
        "name": "KNOW",
        "comment": "",
        "dataType": "",
        "default": "",
        "options": 0,
        "ui": {
          "keys": 0,
          "widthName": 60,
          "widthComment": 60,
          "widthDataType": 60,
          "widthDefault": 60
        },
        "meta": {
          "updateAt": 1736702707955,
          "createAt": 1736702707955
        }
      },
      "Pmd4lMZ3dusQ_OwGfClQq": {
        "id": "Pmd4lMZ3dusQ_OwGfClQq",
        "tableId": "SqYiebLmcDURAb6N2ySGi",
        "name": "--",
        "comment": "",
        "dataType": "NUMBER",
        "default": "",
        "options": 2,
        "ui": {
          "keys": 1,
          "widthName": 60,
          "widthComment": 60,
          "widthDataType": 60,
          "widthDefault": 60
        },
        "meta": {
          "updateAt": 1736702707955,
          "createAt": 1736702707955
        }
      },
      "-5O24mSs_8ImqSjB0VUIP": {
        "id": "-5O24mSs_8ImqSjB0VUIP",
        "tableId": "SqYiebLmcDURAb6N2ySGi",
        "name": "--",
        "comment": "",
        "dataType": "NUMBER",
        "default": "",
        "options": 8,
        "ui": {
          "keys": 0,
          "widthName": 60,
          "widthComment": 60,
          "widthDataType": 60,
          "widthDefault": 60
        },
        "meta": {
          "updateAt": 1736702707955,
          "createAt": 1736702707955
        }
      },
      "2a3OQt8WWnL4WCseyfjwk": {
        "id": "2a3OQt8WWnL4WCseyfjwk",
        "tableId": "SqYiebLmcDURAb6N2ySGi",
        "name": "--",
        "comment": "",
        "dataType": "VARCHAR2(100)",
        "default": "",
        "options": 8,
        "ui": {
          "keys": 0,
          "widthName": 60,
          "widthComment": 60,
          "widthDataType": 87,
          "widthDefault": 60
        },
        "meta": {
          "updateAt": 1736702707955,
          "createAt": 1736702707955
        }
      },
      "0b6nUjVVEOP-hMpDoQtk0": {
        "id": "0b6nUjVVEOP-hMpDoQtk0",
        "tableId": "SqYiebLmcDURAb6N2ySGi",
        "name": "--",
        "comment": "",
        "dataType": "",
        "default": "",
        "options": 0,
        "ui": {
          "keys": 0,
          "widthName": 60,
          "widthComment": 60,
          "widthDataType": 60,
          "widthDefault": 60
        },
        "meta": {
          "updateAt": 1736702707955,
          "createAt": 1736702707955
        }
      },
      "buTj5eCOWMiFDYUcx6L3Q": {
        "id": "buTj5eCOWMiFDYUcx6L3Q",
        "tableId": "PSixUObidiBMOuyFkpVx-",
        "name": "--",
        "comment": "",
        "dataType": "NUMBER",
        "default": "",
        "options": 8,
        "ui": {
          "keys": 0,
          "widthName": 60,
          "widthComment": 60,
          "widthDataType": 60,
          "widthDefault": 60
        },
        "meta": {
          "updateAt": 1736702707955,
          "createAt": 1736702707955
        }
      },
      "wOku0Vert2tr00YvbWE9e": {
        "id": "wOku0Vert2tr00YvbWE9e",
        "tableId": "PSixUObidiBMOuyFkpVx-",
        "name": "--",
        "comment": "",
        "dataType": "NUMBER",
        "default": "",
        "options": 8,
        "ui": {
          "keys": 0,
          "widthName": 60,
          "widthComment": 60,
          "widthDataType": 60,
          "widthDefault": 60
        },
        "meta": {
          "updateAt": 1736702707955,
          "createAt": 1736702707955
        }
      },
      "KIxy7rhwLyrpEbziSnQKW": {
        "id": "KIxy7rhwLyrpEbziSnQKW",
        "tableId": "PSixUObidiBMOuyFkpVx-",
        "name": "--",
        "comment": "",
        "dataType": "",
        "default": "",
        "options": 0,
        "ui": {
          "keys": 0,
          "widthName": 60,
          "widthComment": 60,
          "widthDataType": 60,
          "widthDefault": 60
        },
        "meta": {
          "updateAt": 1736702707955,
          "createAt": 1736702707955
        }
      },
      "GFSJj8RukHLiu4IIuNI96": {
        "id": "GFSJj8RukHLiu4IIuNI96",
        "tableId": "PSixUObidiBMOuyFkpVx-",
        "name": "--",
        "comment": "",
        "dataType": "",
        "default": "",
        "options": 0,
        "ui": {
          "keys": 0,
          "widthName": 60,
          "widthComment": 60,
          "widthDataType": 60,
          "widthDefault": 60
        },
        "meta": {
          "updateAt": 1736702707955,
          "createAt": 1736702707955
        }
      },
      "eLtP_xMEI2fH82_btjgyW": {
        "id": "eLtP_xMEI2fH82_btjgyW",
        "tableId": "PSixUObidiBMOuyFkpVx-",
        "name": "--",
        "comment": "",
        "dataType": "",
        "default": "",
        "options": 0,
        "ui": {
          "keys": 0,
          "widthName": 60,
          "widthComment": 60,
          "widthDataType": 60,
          "widthDefault": 60
        },
        "meta": {
          "updateAt": 1736702707955,
          "createAt": 1736702707955
        }
      },
      "H7XtImL3BqpVIWNl6J-Rc": {
        "id": "H7XtImL3BqpVIWNl6J-Rc",
        "tableId": "nYMkVPha8876Ydb9JLfWN",
        "name": "--",
        "comment": "",
        "dataType": "NUMBER",
        "default": "",
        "options": 2,
        "ui": {
          "keys": 1,
          "widthName": 60,
          "widthComment": 60,
          "widthDataType": 60,
          "widthDefault": 60
        },
        "meta": {
          "updateAt": 1736702707955,
          "createAt": 1736702707955
        }
      },
      "5TlSk2kpdl3QuiYTqEbAs": {
        "id": "5TlSk2kpdl3QuiYTqEbAs",
        "tableId": "nYMkVPha8876Ydb9JLfWN",
        "name": "--",
        "comment": "",
        "dataType": "VARCHAR2(50)",
        "default": "",
        "options": 8,
        "ui": {
          "keys": 0,
          "widthName": 60,
          "widthComment": 60,
          "widthDataType": 81,
          "widthDefault": 60
        },
        "meta": {
          "updateAt": 1736702707955,
          "createAt": 1736702707955
        }
      },
      "aU7jJGc7hY3rTNfEjv0A9": {
        "id": "aU7jJGc7hY3rTNfEjv0A9",
        "tableId": "nYMkVPha8876Ydb9JLfWN",
        "name": "--",
        "comment": "",
        "dataType": "BLOB",
        "default": "",
        "options": 0,
        "ui": {
          "keys": 0,
          "widthName": 60,
          "widthComment": 60,
          "widthDataType": 60,
          "widthDefault": 60
        },
        "meta": {
          "updateAt": 1736702707955,
          "createAt": 1736702707955
        }
      },
      "3tVvmxX4LGr0f3Cghb8MW": {
        "id": "3tVvmxX4LGr0f3Cghb8MW",
        "tableId": "nYMkVPha8876Ydb9JLfWN",
        "name": "--",
        "comment": "",
        "dataType": "VARCHAR2(6)",
        "default": "",
        "options": 8,
        "ui": {
          "keys": 0,
          "widthName": 60,
          "widthComment": 60,
          "widthDataType": 75,
          "widthDefault": 60
        },
        "meta": {
          "updateAt": 1736702707955,
          "createAt": 1736702707955
        }
      },
      "8nJpKWjZZa2OAjWUxd1OL": {
        "id": "8nJpKWjZZa2OAjWUxd1OL",
        "tableId": "nYMkVPha8876Ydb9JLfWN",
        "name": "--",
        "comment": "",
        "dataType": "TIMESTAMP",
        "default": "CURRENT_TIMESTAMP",
        "options": 0,
        "ui": {
          "keys": 0,
          "widthName": 60,
          "widthComment": 60,
          "widthDataType": 65,
          "widthDefault": 122
        },
        "meta": {
          "updateAt": 1736702707955,
          "createAt": 1736702707955
        }
      },
      "2VuRUzikZMV5NmZ5SjYLI": {
        "id": "2VuRUzikZMV5NmZ5SjYLI",
        "tableId": "ZD717xZ8SsmzE0VdbKCpX",
        "name": "LOG_ID",
        "comment": "",
        "dataType": "NUMBER",
        "default": "",
        "options": 2,
        "ui": {
          "keys": 1,
          "widthName": 60,
          "widthComment": 60,
          "widthDataType": 60,
          "widthDefault": 60
        },
        "meta": {
          "updateAt": 1736702707955,
          "createAt": 1736702707955
        }
      },
      "20IEpBfSw605VyedgdRu6": {
        "id": "20IEpBfSw605VyedgdRu6",
        "tableId": "ZD717xZ8SsmzE0VdbKCpX",
        "name": "CHANGER",
        "comment": "",
        "dataType": "VARCHAR2(40)",
        "default": "",
        "options": 8,
        "ui": {
          "keys": 0,
          "widthName": 60,
          "widthComment": 60,
          "widthDataType": 81,
          "widthDefault": 60
        },
        "meta": {
          "updateAt": 1736702707955,
          "createAt": 1736702707955
        }
      },
      "3bgi4hf0Lymg0LrSlY29J": {
        "id": "3bgi4hf0Lymg0LrSlY29J",
        "tableId": "ZD717xZ8SsmzE0VdbKCpX",
        "name": "LOG_MSSG",
        "comment": "",
        "dataType": "VARCHAR2(1000)",
        "default": "",
        "options": 8,
        "ui": {
          "keys": 0,
          "widthName": 61,
          "widthComment": 60,
          "widthDataType": 94,
          "widthDefault": 60
        },
        "meta": {
          "updateAt": 1736702707956,
          "createAt": 1736702707956
        }
      },
      "olq7d54JcM9-pfnyuEjfD": {
        "id": "olq7d54JcM9-pfnyuEjfD",
        "tableId": "ZD717xZ8SsmzE0VdbKCpX",
        "name": "MODIFIED_TABLE",
        "comment": "",
        "dataType": "VARCHAR2(30)",
        "default": "",
        "options": 8,
        "ui": {
          "keys": 0,
          "widthName": 94,
          "widthComment": 60,
          "widthDataType": 81,
          "widthDefault": 60
        },
        "meta": {
          "updateAt": 1736702707956,
          "createAt": 1736702707956
        }
      },
      "VFRLCkLYuc3MH3SN503mh": {
        "id": "VFRLCkLYuc3MH3SN503mh",
        "tableId": "ZD717xZ8SsmzE0VdbKCpX",
        "name": "TR_NAME",
        "comment": "",
        "dataType": "VARCHAR2(30)",
        "default": "",
        "options": 8,
        "ui": {
          "keys": 0,
          "widthName": 60,
          "widthComment": 60,
          "widthDataType": 81,
          "widthDefault": 60
        },
        "meta": {
          "updateAt": 1736702707956,
          "createAt": 1736702707956
        }
      },
      "BR4gU5CbfHp7LTF68h8R9": {
        "id": "BR4gU5CbfHp7LTF68h8R9",
        "tableId": "ZD717xZ8SsmzE0VdbKCpX",
        "name": "TR_TIME",
        "comment": "",
        "dataType": "TIMESTAMP",
        "default": "CURRENT_TIMESTAMP",
        "options": 0,
        "ui": {
          "keys": 0,
          "widthName": 60,
          "widthComment": 60,
          "widthDataType": 65,
          "widthDefault": 122
        },
        "meta": {
          "updateAt": 1736702707956,
          "createAt": 1736702707956
        }
      },
      "nxWRQ3uFF4R9GXteaHlqv": {
        "id": "nxWRQ3uFF4R9GXteaHlqv",
        "tableId": "p0KeMVCBdrcK4MmNpbWLc",
        "name": "LOG_ID",
        "comment": "",
        "dataType": "NUMBER",
        "default": "",
        "options": 2,
        "ui": {
          "keys": 1,
          "widthName": 60,
          "widthComment": 60,
          "widthDataType": 60,
          "widthDefault": 60
        },
        "meta": {
          "updateAt": 1736702707956,
          "createAt": 1736702707956
        }
      },
      "uLurIyYTqHdPyrK2lk66H": {
        "id": "uLurIyYTqHdPyrK2lk66H",
        "tableId": "p0KeMVCBdrcK4MmNpbWLc",
        "name": "CHANGER",
        "comment": "",
        "dataType": "VARCHAR2(40)",
        "default": "",
        "options": 8,
        "ui": {
          "keys": 0,
          "widthName": 60,
          "widthComment": 60,
          "widthDataType": 81,
          "widthDefault": 60
        },
        "meta": {
          "updateAt": 1736702707956,
          "createAt": 1736702707956
        }
      },
      "86Z8T4b70WmW1LelP0fqS": {
        "id": "86Z8T4b70WmW1LelP0fqS",
        "tableId": "p0KeMVCBdrcK4MmNpbWLc",
        "name": "LOG_MSSG",
        "comment": "",
        "dataType": "VARCHAR2(1000)",
        "default": "",
        "options": 8,
        "ui": {
          "keys": 0,
          "widthName": 61,
          "widthComment": 60,
          "widthDataType": 94,
          "widthDefault": 60
        },
        "meta": {
          "updateAt": 1736702707956,
          "createAt": 1736702707956
        }
      },
      "qt9F3TQ07Ot8EQFHYnqFc": {
        "id": "qt9F3TQ07Ot8EQFHYnqFc",
        "tableId": "p0KeMVCBdrcK4MmNpbWLc",
        "name": "MODIFIED_TABLE",
        "comment": "",
        "dataType": "VARCHAR2(30)",
        "default": "",
        "options": 8,
        "ui": {
          "keys": 0,
          "widthName": 94,
          "widthComment": 60,
          "widthDataType": 81,
          "widthDefault": 60
        },
        "meta": {
          "updateAt": 1736702707956,
          "createAt": 1736702707956
        }
      },
      "A0ZJN0fGojyGIhR_A5qKU": {
        "id": "A0ZJN0fGojyGIhR_A5qKU",
        "tableId": "p0KeMVCBdrcK4MmNpbWLc",
        "name": "TR_NAME",
        "comment": "",
        "dataType": "VARCHAR2(30)",
        "default": "",
        "options": 8,
        "ui": {
          "keys": 0,
          "widthName": 60,
          "widthComment": 60,
          "widthDataType": 81,
          "widthDefault": 60
        },
        "meta": {
          "updateAt": 1736702707956,
          "createAt": 1736702707956
        }
      },
      "WthKAjDF5Br4Wrb47E96q": {
        "id": "WthKAjDF5Br4Wrb47E96q",
        "tableId": "p0KeMVCBdrcK4MmNpbWLc",
        "name": "TR_TIME",
        "comment": "",
        "dataType": "TIMESTAMP",
        "default": "CURRENT_TIMESTAMP",
        "options": 0,
        "ui": {
          "keys": 0,
          "widthName": 60,
          "widthComment": 60,
          "widthDataType": 65,
          "widthDefault": 122
        },
        "meta": {
          "updateAt": 1736702707956,
          "createAt": 1736702707956
        }
      },
      "awtTXq63QYzGVq2jUe6Hc": {
        "id": "awtTXq63QYzGVq2jUe6Hc",
        "tableId": "SdRYuoMaQMiVi-syV-iNu",
        "name": "LOG_ID",
        "comment": "",
        "dataType": "NUMBER",
        "default": "",
        "options": 2,
        "ui": {
          "keys": 1,
          "widthName": 60,
          "widthComment": 60,
          "widthDataType": 60,
          "widthDefault": 60
        },
        "meta": {
          "updateAt": 1736702707956,
          "createAt": 1736702707956
        }
      },
      "lhEwzoXcgOL84TcjnGUze": {
        "id": "lhEwzoXcgOL84TcjnGUze",
        "tableId": "SdRYuoMaQMiVi-syV-iNu",
        "name": "CHANGER",
        "comment": "",
        "dataType": "VARCHAR2(40)",
        "default": "",
        "options": 8,
        "ui": {
          "keys": 0,
          "widthName": 60,
          "widthComment": 60,
          "widthDataType": 81,
          "widthDefault": 60
        },
        "meta": {
          "updateAt": 1736702707956,
          "createAt": 1736702707956
        }
      },
      "ztY8UuGKH_RwjZv6SBKQV": {
        "id": "ztY8UuGKH_RwjZv6SBKQV",
        "tableId": "SdRYuoMaQMiVi-syV-iNu",
        "name": "LOG_MSSG",
        "comment": "",
        "dataType": "VARCHAR2(1000)",
        "default": "",
        "options": 8,
        "ui": {
          "keys": 0,
          "widthName": 61,
          "widthComment": 60,
          "widthDataType": 94,
          "widthDefault": 60
        },
        "meta": {
          "updateAt": 1736702707956,
          "createAt": 1736702707956
        }
      },
      "16p46SJ5NllCORM8Q9zEw": {
        "id": "16p46SJ5NllCORM8Q9zEw",
        "tableId": "SdRYuoMaQMiVi-syV-iNu",
        "name": "MODIFIED_TABLE",
        "comment": "",
        "dataType": "VARCHAR2(30)",
        "default": "",
        "options": 8,
        "ui": {
          "keys": 0,
          "widthName": 94,
          "widthComment": 60,
          "widthDataType": 81,
          "widthDefault": 60
        },
        "meta": {
          "updateAt": 1736702707956,
          "createAt": 1736702707956
        }
      },
      "XPiBBVN14JF8FPMEpplmb": {
        "id": "XPiBBVN14JF8FPMEpplmb",
        "tableId": "SdRYuoMaQMiVi-syV-iNu",
        "name": "TR_NAME",
        "comment": "",
        "dataType": "VARCHAR2(30)",
        "default": "",
        "options": 8,
        "ui": {
          "keys": 0,
          "widthName": 60,
          "widthComment": 60,
          "widthDataType": 81,
          "widthDefault": 60
        },
        "meta": {
          "updateAt": 1736702707956,
          "createAt": 1736702707956
        }
      },
      "I9gspjYcfIm-jsNp1Q6Nh": {
        "id": "I9gspjYcfIm-jsNp1Q6Nh",
        "tableId": "SdRYuoMaQMiVi-syV-iNu",
        "name": "TR_TIME",
        "comment": "",
        "dataType": "TIMESTAMP",
        "default": "CURRENT_TIMESTAMP",
        "options": 0,
        "ui": {
          "keys": 0,
          "widthName": 60,
          "widthComment": 60,
          "widthDataType": 65,
          "widthDefault": 122
        },
        "meta": {
          "updateAt": 1736702707956,
          "createAt": 1736702707956
        }
      },
      "qKuJI7UA9_ihsMo4t5S1v": {
        "id": "qKuJI7UA9_ihsMo4t5S1v",
        "tableId": "PFV4tkpKUrgv3L36oIFpE",
        "name": "LOG_ID",
        "comment": "",
        "dataType": "NUMBER",
        "default": "",
        "options": 2,
        "ui": {
          "keys": 1,
          "widthName": 60,
          "widthComment": 60,
          "widthDataType": 60,
          "widthDefault": 60
        },
        "meta": {
          "updateAt": 1736702707956,
          "createAt": 1736702707956
        }
      },
      "g1rwiOXt0w72YMkqq-HHd": {
        "id": "g1rwiOXt0w72YMkqq-HHd",
        "tableId": "PFV4tkpKUrgv3L36oIFpE",
        "name": "CHANGER",
        "comment": "",
        "dataType": "VARCHAR2(40)",
        "default": "",
        "options": 8,
        "ui": {
          "keys": 0,
          "widthName": 60,
          "widthComment": 60,
          "widthDataType": 81,
          "widthDefault": 60
        },
        "meta": {
          "updateAt": 1736702707956,
          "createAt": 1736702707956
        }
      },
      "BSzM84CZcFOJAaErM5RET": {
        "id": "BSzM84CZcFOJAaErM5RET",
        "tableId": "PFV4tkpKUrgv3L36oIFpE",
        "name": "LOG_MSSG",
        "comment": "",
        "dataType": "VARCHAR2(1000)",
        "default": "",
        "options": 8,
        "ui": {
          "keys": 0,
          "widthName": 61,
          "widthComment": 60,
          "widthDataType": 94,
          "widthDefault": 60
        },
        "meta": {
          "updateAt": 1736702707956,
          "createAt": 1736702707956
        }
      },
      "eoz9pYj0kfTXNHdqgF8ZR": {
        "id": "eoz9pYj0kfTXNHdqgF8ZR",
        "tableId": "PFV4tkpKUrgv3L36oIFpE",
        "name": "MODIFIED_TABLE",
        "comment": "",
        "dataType": "VARCHAR2(30)",
        "default": "",
        "options": 8,
        "ui": {
          "keys": 0,
          "widthName": 94,
          "widthComment": 60,
          "widthDataType": 81,
          "widthDefault": 60
        },
        "meta": {
          "updateAt": 1736702707956,
          "createAt": 1736702707956
        }
      },
      "Kt9YjqnKAS6aUKMoKlSDa": {
        "id": "Kt9YjqnKAS6aUKMoKlSDa",
        "tableId": "PFV4tkpKUrgv3L36oIFpE",
        "name": "TR_NAME",
        "comment": "",
        "dataType": "VARCHAR2(30)",
        "default": "",
        "options": 8,
        "ui": {
          "keys": 0,
          "widthName": 60,
          "widthComment": 60,
          "widthDataType": 81,
          "widthDefault": 60
        },
        "meta": {
          "updateAt": 1736702707956,
          "createAt": 1736702707956
        }
      },
      "3dIHwknTbE-87xtJGfmhX": {
        "id": "3dIHwknTbE-87xtJGfmhX",
        "tableId": "PFV4tkpKUrgv3L36oIFpE",
        "name": "TR_TIME",
        "comment": "",
        "dataType": "TIMESTAMP",
        "default": "CURRENT_TIMESTAMP",
        "options": 0,
        "ui": {
          "keys": 0,
          "widthName": 60,
          "widthComment": 60,
          "widthDataType": 65,
          "widthDefault": 122
        },
        "meta": {
          "updateAt": 1736702707956,
          "createAt": 1736702707956
        }
      }
    },
    "relationshipEntities": {
      "Wxc-MeJHW1ZT56NhwTkEY": {
        "id": "Wxc-MeJHW1ZT56NhwTkEY",
        "identification": false,
        "relationshipType": 4,
        "startRelationshipType": 1,
        "start": {
          "tableId": "QJEdFeKsrm8oSCMS_Se_k",
          "columnIds": [
            "tp3ydmosVp2zAr3aq-mZe"
          ],
          "x": 917.9747,
          "y": 318.81010000000003,
          "direction": 2
        },
        "end": {
          "tableId": "cQpUxLpOYUyxPH0YoHluk",
          "columnIds": [
            "3ia5CK-15TX_ZMuSzNdob"
          ],
          "x": 1506.4029666666665,
          "y": 1967.7414,
          "direction": 4
        },
        "meta": {
          "updateAt": 1736702707956,
          "createAt": 1736702707956
        }
      },
      "V9oI-ZK6N58bKgZvBpIWR": {
        "id": "V9oI-ZK6N58bKgZvBpIWR",
        "identification": false,
        "relationshipType": 4,
        "startRelationshipType": 1,
        "start": {
          "tableId": "cQTtce6Cto28iUz5GpSII",
          "columnIds": [
            "jGU9HI-YFyQ9eNhgb1SdC"
          ],
          "x": 1052.25,
          "y": 178,
          "direction": 8
        },
        "end": {
          "tableId": "cQpUxLpOYUyxPH0YoHluk",
          "columnIds": [
            "-tslz2qAlyGvJJWyH6mXH"
          ],
          "x": 1760.9029666666663,
          "y": 1967.7414,
          "direction": 4
        },
        "meta": {
          "updateAt": 1736702707956,
          "createAt": 1736702707956
        }
      },
      "cE2F20He112VIbFvzUl-G": {
        "id": "cE2F20He112VIbFvzUl-G",
        "identification": true,
        "relationshipType": 4,
        "startRelationshipType": 2,
        "start": {
          "tableId": "_DQoyIW0mWh4yxWzDoo-q",
          "columnIds": [
            "pIDdVjOp3mnUcXmR68tPu"
          ],
          "x": 436.4755,
          "y": 2080.8197,
          "direction": 2
        },
        "end": {
          "tableId": "8EodW7KK530D9bHNIN4vC",
          "columnIds": [
            "_UZYBkq119OtyC2Li4acS"
          ],
          "x": 711.3935,
          "y": 2123.3115,
          "direction": 1
        },
        "meta": {
          "updateAt": 1736702707956,
          "createAt": 1736702707956
        }
      },
      "5f1oCKFwmtX1du7CPKK2P": {
        "id": "5f1oCKFwmtX1du7CPKK2P",
        "identification": true,
        "relationshipType": 4,
        "startRelationshipType": 2,
        "start": {
          "tableId": "cQpUxLpOYUyxPH0YoHluk",
          "columnIds": [
            "BhinAjCHkM-EZJ2qpB14B"
          ],
          "x": 1463.9863,
          "y": 2234.408066666667,
          "direction": 1
        },
        "end": {
          "tableId": "8EodW7KK530D9bHNIN4vC",
          "columnIds": [
            "XvmTxiDYWd8reNv6JBG1f"
          ],
          "x": 1085.3935000000001,
          "y": 2123.3115,
          "direction": 2
        },
        "meta": {
          "updateAt": 1736702707956,
          "createAt": 1736702707956
        }
      },
      "ThldVzlAFWhkoWyX7qM5_": {
        "id": "ThldVzlAFWhkoWyX7qM5_",
        "identification": false,
        "relationshipType": 4,
        "startRelationshipType": 2,
        "start": {
          "tableId": "cQpUxLpOYUyxPH0YoHluk",
          "columnIds": [
            "BhinAjCHkM-EZJ2qpB14B"
          ],
          "x": 1463.9863,
          "y": 2021.0747333333336,
          "direction": 1
        },
        "end": {
          "tableId": "ZlJvFqugz39C-zOVp8Niy",
          "columnIds": [
            "Jds6IawjmIAeVJtD3Em2e"
          ],
          "x": 511,
          "y": 334,
          "direction": 2
        },
        "meta": {
          "updateAt": 1736702707956,
          "createAt": 1736702707956
        }
      },
      "RCUsSrmZ20AV05whPsOdv": {
        "id": "RCUsSrmZ20AV05whPsOdv",
        "identification": false,
        "relationshipType": 4,
        "startRelationshipType": 2,
        "start": {
          "tableId": "cQTtce6Cto28iUz5GpSII",
          "columnIds": [
            "jGU9HI-YFyQ9eNhgb1SdC"
          ],
          "x": 949,
          "y": 114,
          "direction": 1
        },
        "end": {
          "tableId": "QJEdFeKsrm8oSCMS_Se_k",
          "columnIds": [
            "6rs_DKqDGC78tVUBATcQ0"
          ],
          "x": 917.9747,
          "y": 268.14343333333335,
          "direction": 2
        },
        "meta": {
          "updateAt": 1736702707957,
          "createAt": 1736702707957
        }
      },
      "7HsHZ77Xeld2vj0ClxbHL": {
        "id": "7HsHZ77Xeld2vj0ClxbHL",
        "identification": false,
        "relationshipType": 4,
        "startRelationshipType": 1,
        "start": {
          "tableId": "cQpUxLpOYUyxPH0YoHluk",
          "columnIds": [
            "BhinAjCHkM-EZJ2qpB14B"
          ],
          "x": 1591.2362999999998,
          "y": 1967.7414,
          "direction": 4
        },
        "end": {
          "tableId": "QJEdFeKsrm8oSCMS_Se_k",
          "columnIds": [
            "5kxByovBBYWdD-K23zLAq"
          ],
          "x": 917.9747,
          "y": 369.4767666666667,
          "direction": 2
        },
        "meta": {
          "updateAt": 1736702707957,
          "createAt": 1736702707957
        }
      },
      "J0r_XiQKjQQIzQTNMrS-x": {
        "id": "J0r_XiQKjQQIzQTNMrS-x",
        "identification": false,
        "relationshipType": 4,
        "startRelationshipType": 1,
        "start": {
          "tableId": "cQpUxLpOYUyxPH0YoHluk",
          "columnIds": [
            "BhinAjCHkM-EZJ2qpB14B"
          ],
          "x": 1845.7362999999996,
          "y": 1967.7414,
          "direction": 4
        },
        "end": {
          "tableId": "cQTtce6Cto28iUz5GpSII",
          "columnIds": [
            "XRdIym3dC9bVp7iovgy19"
          ],
          "x": 1258.75,
          "y": 178,
          "direction": 8
        },
        "meta": {
          "updateAt": 1736702707957,
          "createAt": 1736702707957
        }
      },
      "2QpcLALFODdGwFpQvhSGU": {
        "id": "2QpcLALFODdGwFpQvhSGU",
        "identification": false,
        "relationshipType": 4,
        "startRelationshipType": 2,
        "start": {
          "tableId": "4f9Z8zFWxVX8rBoWBLdhW",
          "columnIds": [
            "-Dib_cMyUHkBlVZpEQhdj"
          ],
          "x": 1856.3793,
          "y": 1228.7586,
          "direction": 1
        },
        "end": {
          "tableId": "i1fNivitx70K1rJyaTswC",
          "columnIds": [
            "Lzcu_RWaPnSpqReq4cY-m"
          ],
          "x": 531,
          "y": 796,
          "direction": 2
        },
        "meta": {
          "updateAt": 1736702707957,
          "createAt": 1736702707957
        }
      },
      "P4LBinmzTXAlwY7JPjiiq": {
        "id": "P4LBinmzTXAlwY7JPjiiq",
        "identification": false,
        "relationshipType": 4,
        "startRelationshipType": 2,
        "start": {
          "tableId": "cQpUxLpOYUyxPH0YoHluk",
          "columnIds": [
            "BhinAjCHkM-EZJ2qpB14B"
          ],
          "x": 1463.9863,
          "y": 2127.7414000000003,
          "direction": 1
        },
        "end": {
          "tableId": "i1fNivitx70K1rJyaTswC",
          "columnIds": [
            "m6eIJyLVOZV0CvjNu8HYN"
          ],
          "x": 531,
          "y": 896,
          "direction": 2
        },
        "meta": {
          "updateAt": 1736702707957,
          "createAt": 1736702707957
        }
      },
      "H-Fjlw4XC68En84lQm_iG": {
        "id": "H-Fjlw4XC68En84lQm_iG",
        "identification": false,
        "relationshipType": 4,
        "startRelationshipType": 2,
        "start": {
          "tableId": "cQpUxLpOYUyxPH0YoHluk",
          "columnIds": [
            "BhinAjCHkM-EZJ2qpB14B"
          ],
          "x": 1676.069633333333,
          "y": 1967.7414,
          "direction": 4
        },
        "end": {
          "tableId": "C0RjPc1YqTUs69VpM8yqs",
          "columnIds": [
            "pyc8UEooyewc6SbjmsJSQ"
          ],
          "x": 1085,
          "y": 846,
          "direction": 2
        },
        "meta": {
          "updateAt": 1736702707957,
          "createAt": 1736702707957
        }
      },
      "6Jvqfa-HJP49rLv3E6wV9": {
        "id": "6Jvqfa-HJP49rLv3E6wV9",
        "identification": false,
        "relationshipType": 4,
        "startRelationshipType": 2,
        "start": {
          "tableId": "QJEdFeKsrm8oSCMS_Se_k",
          "columnIds": [
            "tp3ydmosVp2zAr3aq-mZe"
          ],
          "x": 723.4747,
          "y": 394.81010000000003,
          "direction": 8
        },
        "end": {
          "tableId": "C0RjPc1YqTUs69VpM8yqs",
          "columnIds": [
            "JQYN-i48j14DjN2aLyhVF"
          ],
          "x": 848,
          "y": 746,
          "direction": 4
        },
        "meta": {
          "updateAt": 1736702707957,
          "createAt": 1736702707957
        }
      },
      "vBZ13bfSrtfMJrDu2oMlI": {
        "id": "vBZ13bfSrtfMJrDu2oMlI",
        "identification": true,
        "relationshipType": 4,
        "startRelationshipType": 2,
        "start": {
          "tableId": "4f9Z8zFWxVX8rBoWBLdhW",
          "columnIds": [
            "-Dib_cMyUHkBlVZpEQhdj"
          ],
          "x": 1856.3793,
          "y": 1128.7586,
          "direction": 1
        },
        "end": {
          "tableId": "BNYvo6am8pGrh89TE7PeE",
          "columnIds": [
            "FlWqDZnzpNR15ceY0azGe"
          ],
          "x": 1528,
          "y": 372,
          "direction": 2
        },
        "meta": {
          "updateAt": 1736702707957,
          "createAt": 1736702707957
        }
      },
      "Ffb7UaXenSEDOHDfCvD42": {
        "id": "Ffb7UaXenSEDOHDfCvD42",
        "identification": true,
        "relationshipType": 4,
        "startRelationshipType": 2,
        "start": {
          "tableId": "OZtvqGyIw6mxj-R7hbeDW",
          "columnIds": [
            "1gDP3KCwX9PajEyfDR8cM"
          ],
          "x": 1663,
          "y": 178,
          "direction": 8
        },
        "end": {
          "tableId": "BNYvo6am8pGrh89TE7PeE",
          "columnIds": [
            "yMvFNVBymrcYCQDEH__JX"
          ],
          "x": 1528,
          "y": 296,
          "direction": 2
        },
        "meta": {
          "updateAt": 1736702707957,
          "createAt": 1736702707957
        }
      },
      "3vNnu6Q5b0ul3mfZ4hUCe": {
        "id": "3vNnu6Q5b0ul3mfZ4hUCe",
        "identification": true,
        "relationshipType": 4,
        "startRelationshipType": 2,
        "start": {
          "tableId": "cQpUxLpOYUyxPH0YoHluk",
          "columnIds": [
            "BhinAjCHkM-EZJ2qpB14B"
          ],
          "x": 1930.5696333333328,
          "y": 1967.7414,
          "direction": 4
        },
        "end": {
          "tableId": "BNYvo6am8pGrh89TE7PeE",
          "columnIds": [
            "mwc_ZUEaAxNTBQClIG0fn"
          ],
          "x": 1294,
          "y": 410,
          "direction": 8
        },
        "meta": {
          "updateAt": 1736702707957,
          "createAt": 1736702707957
        }
      },
      "p_eNM2JtN4Qkti5xh_j-v": {
        "id": "p_eNM2JtN4Qkti5xh_j-v",
        "identification": true,
        "relationshipType": 4,
        "startRelationshipType": 2,
        "start": {
          "tableId": "cQpUxLpOYUyxPH0YoHluk",
          "columnIds": [
            "BhinAjCHkM-EZJ2qpB14B"
          ],
          "x": 75.45,
          "y": 1634,
          "direction": 4
        },
        "end": {
          "tableId": "SqYiebLmcDURAb6N2ySGi",
          "columnIds": [],
          "x": 246,
          "y": 642,
          "direction": 8
        },
        "meta": {
          "updateAt": 1736702707957,
          "createAt": 1736702707957
        }
      },
      "zWvLS_X29EtgYHLoUauw0": {
        "id": "zWvLS_X29EtgYHLoUauw0",
        "identification": true,
        "relationshipType": 4,
        "startRelationshipType": 2,
        "start": {
          "tableId": "SqYiebLmcDURAb6N2ySGi",
          "columnIds": [],
          "x": 442,
          "y": 566,
          "direction": 2
        },
        "end": {
          "tableId": "PSixUObidiBMOuyFkpVx-",
          "columnIds": [],
          "x": 522,
          "y": 578,
          "direction": 1
        },
        "meta": {
          "updateAt": 1736702707957,
          "createAt": 1736702707957
        }
      },
      "t-7kJta5v01NuAdhC0h9g": {
        "id": "t-7kJta5v01NuAdhC0h9g",
        "identification": true,
        "relationshipType": 4,
        "startRelationshipType": 2,
        "start": {
          "tableId": "nYMkVPha8876Ydb9JLfWN",
          "columnIds": [],
          "x": 967,
          "y": 578,
          "direction": 1
        },
        "end": {
          "tableId": "PSixUObidiBMOuyFkpVx-",
          "columnIds": [],
          "x": 887,
          "y": 578,
          "direction": 2
        },
        "meta": {
          "updateAt": 1736702707957,
          "createAt": 1736702707957
        }
      }
    },
    "indexEntities": {
      "_1Z0QCT9wykLMBDGwmPY9": {
        "id": "_1Z0QCT9wykLMBDGwmPY9",
        "name": "MEMBER_NAME_I",
        "tableId": "cQpUxLpOYUyxPH0YoHluk",
        "indexColumnIds": [
          "bvXUeH-3VL9RDjUWhyIDD",
          "Jv3gUWL4GJHOVM8FFTcC6"
        ],
        "seqIndexColumnIds": [
          "bvXUeH-3VL9RDjUWhyIDD",
          "Jv3gUWL4GJHOVM8FFTcC6"
        ],
        "unique": false,
        "meta": {
          "updateAt": 1736702707957,
          "createAt": 1736702707957
        }
      },
      "os9NW01l8H4Gna6ODq15Y": {
        "id": "os9NW01l8H4Gna6ODq15Y",
        "name": "MEMBERS_M_I",
        "tableId": "cQpUxLpOYUyxPH0YoHluk",
        "indexColumnIds": [
          "8PYpdgEoe43SnaPTypdoI",
          "zOnjlH8EJIh4puhCncrmV",
          "4_8jVskg-mk7cJq4dAl89"
        ],
        "seqIndexColumnIds": [
          "8PYpdgEoe43SnaPTypdoI",
          "zOnjlH8EJIh4puhCncrmV",
          "4_8jVskg-mk7cJq4dAl89"
        ],
        "unique": false,
        "meta": {
          "updateAt": 1736702707957,
          "createAt": 1736702707957
        }
      },
      "vDbYEE0Td6tmT1LAo__F1": {
        "id": "vDbYEE0Td6tmT1LAo__F1",
        "name": "MEMBERS_ORS_I",
        "tableId": "cQpUxLpOYUyxPH0YoHluk",
        "indexColumnIds": [
          "Nja_C13sqglMFNwW0Lvcz"
        ],
        "seqIndexColumnIds": [
          "Nja_C13sqglMFNwW0Lvcz"
        ],
        "unique": false,
        "meta": {
          "updateAt": 1736702707957,
          "createAt": 1736702707957
        }
      },
      "GQeDEwbWBv53XAZOa3-6r": {
        "id": "GQeDEwbWBv53XAZOa3-6r",
        "name": "ADDRESS_CITY_I",
        "tableId": "_DQoyIW0mWh4yxWzDoo-q",
        "indexColumnIds": [
          "V6MWJDWqVFXqOJw1rxB6_"
        ],
        "seqIndexColumnIds": [
          "V6MWJDWqVFXqOJw1rxB6_"
        ],
        "unique": false,
        "meta": {
          "updateAt": 1736702707957,
          "createAt": 1736702707957
        }
      },
      "lxHCGWl7d3c-4vjPLTTZW": {
        "id": "lxHCGWl7d3c-4vjPLTTZW",
        "name": "ADDRESS_STREET_I",
        "tableId": "_DQoyIW0mWh4yxWzDoo-q",
        "indexColumnIds": [
          "biDrvMwRk0ERNOnjxcXOr"
        ],
        "seqIndexColumnIds": [
          "biDrvMwRk0ERNOnjxcXOr"
        ],
        "unique": false,
        "meta": {
          "updateAt": 1736702707957,
          "createAt": 1736702707957
        }
      },
      "ROQiKfkchgNQ9lum0u_LU": {
        "id": "ROQiKfkchgNQ9lum0u_LU",
        "name": "ADDRESS_FULL_STREET_I",
        "tableId": "_DQoyIW0mWh4yxWzDoo-q",
        "indexColumnIds": [
          "GadMkXXCtysOic5AfURyu",
          "ALiCSzJAGhACwCbXd96Cn",
          "mBkypjbO4mL86AvDL-6AY"
        ],
        "seqIndexColumnIds": [
          "GadMkXXCtysOic5AfURyu",
          "ALiCSzJAGhACwCbXd96Cn",
          "mBkypjbO4mL86AvDL-6AY"
        ],
        "unique": false,
        "meta": {
          "updateAt": 1736702707957,
          "createAt": 1736702707957
        }
      },
      "4iql7GHsUbPfQ-8IgAQP4": {
        "id": "4iql7GHsUbPfQ-8IgAQP4",
        "name": "EVENT_DATE_I",
        "tableId": "4f9Z8zFWxVX8rBoWBLdhW",
        "indexColumnIds": [
          "_qoXwKtBuMliUh9jS-jHn"
        ],
        "seqIndexColumnIds": [
          "_qoXwKtBuMliUh9jS-jHn"
        ],
        "unique": false,
        "meta": {
          "updateAt": 1736702707957,
          "createAt": 1736702707957
        }
      },
      "NB-RmcIf6ALnb61mO8awi": {
        "id": "NB-RmcIf6ALnb61mO8awi",
        "name": "POST_TYPE_I",
        "tableId": "FP9pvGnaKSAM2BqpEAXPU",
        "indexColumnIds": [
          "9jA556-ttukONbrhQKeX4"
        ],
        "seqIndexColumnIds": [
          "9jA556-ttukONbrhQKeX4"
        ],
        "unique": false,
        "meta": {
          "updateAt": 1736702707957,
          "createAt": 1736702707957
        }
      },
      "8cVenpI_1ESF5TY5PaM89": {
        "id": "8cVenpI_1ESF5TY5PaM89",
        "name": "PERSONAL_CHANGER_I",
        "tableId": "ZD717xZ8SsmzE0VdbKCpX",
        "indexColumnIds": [
          "zUuwx7BXLkMq2HNZ9jXul"
        ],
        "seqIndexColumnIds": [
          "zUuwx7BXLkMq2HNZ9jXul"
        ],
        "unique": false,
        "meta": {
          "updateAt": 1736702707957,
          "createAt": 1736702707957
        }
      },
      "lPk3mfR8dzC4qUD4emTgA": {
        "id": "lPk3mfR8dzC4qUD4emTgA",
        "name": "PERSONAL_TABLE_I",
        "tableId": "ZD717xZ8SsmzE0VdbKCpX",
        "indexColumnIds": [
          "-XMUbNvQIrD2pdMcMCbX_"
        ],
        "seqIndexColumnIds": [
          "-XMUbNvQIrD2pdMcMCbX_"
        ],
        "unique": false,
        "meta": {
          "updateAt": 1736702707957,
          "createAt": 1736702707957
        }
      },
      "Mx5c2xDEuWE4m4hzYeQPR": {
        "id": "Mx5c2xDEuWE4m4hzYeQPR",
        "name": "REPORT_CHANGER_I",
        "tableId": "p0KeMVCBdrcK4MmNpbWLc",
        "indexColumnIds": [
          "A5wn8e8-tZjb_1-v885er"
        ],
        "seqIndexColumnIds": [
          "A5wn8e8-tZjb_1-v885er"
        ],
        "unique": false,
        "meta": {
          "updateAt": 1736702707957,
          "createAt": 1736702707957
        }
      },
      "3wXtuYKjLJ9P0YDpkTG6c": {
        "id": "3wXtuYKjLJ9P0YDpkTG6c",
        "name": "REPORT_TABLE_I",
        "tableId": "p0KeMVCBdrcK4MmNpbWLc",
        "indexColumnIds": [
          "aoLIjL9GX6RAyCt5a-MKx"
        ],
        "seqIndexColumnIds": [
          "aoLIjL9GX6RAyCt5a-MKx"
        ],
        "unique": false,
        "meta": {
          "updateAt": 1736702707957,
          "createAt": 1736702707957
        }
      },
      "IXIlEjpm7H0op1E45opbw": {
        "id": "IXIlEjpm7H0op1E45opbw",
        "name": "INTERNAL_ASSIGNS_CHANGER_I",
        "tableId": "SdRYuoMaQMiVi-syV-iNu",
        "indexColumnIds": [
          "62Mslukj6KjDyLvO1dTSa"
        ],
        "seqIndexColumnIds": [
          "62Mslukj6KjDyLvO1dTSa"
        ],
        "unique": false,
        "meta": {
          "updateAt": 1736702707957,
          "createAt": 1736702707957
        }
      },
      "iqgQOG2lKNY6X2euWjYLw": {
        "id": "iqgQOG2lKNY6X2euWjYLw",
        "name": "INTERNAL_ASSIGNS_TABLE_I",
        "tableId": "SdRYuoMaQMiVi-syV-iNu",
        "indexColumnIds": [
          "6svYBCwGBsY3egYFIMdCG"
        ],
        "seqIndexColumnIds": [
          "6svYBCwGBsY3egYFIMdCG"
        ],
        "unique": false,
        "meta": {
          "updateAt": 1736702707958,
          "createAt": 1736702707958
        }
      },
      "FtfUYi84Zm0v5zf7mXvUp": {
        "id": "FtfUYi84Zm0v5zf7mXvUp",
        "name": "PUBLIC_ACTIVITIES_CHANGER_I",
        "tableId": "PFV4tkpKUrgv3L36oIFpE",
        "indexColumnIds": [
          "3HhyLUreDudy6g3DEfLYv"
        ],
        "seqIndexColumnIds": [
          "3HhyLUreDudy6g3DEfLYv"
        ],
        "unique": false,
        "meta": {
          "updateAt": 1736702707958,
          "createAt": 1736702707958
        }
      },
      "zgJfD-iclW_Uk-tMJ9fkz": {
        "id": "zgJfD-iclW_Uk-tMJ9fkz",
        "name": "PUBLIC_ACTIVITIES_TABLE_I",
        "tableId": "PFV4tkpKUrgv3L36oIFpE",
        "indexColumnIds": [
          "X_7B3TtFbetrabTVnrbFV"
        ],
        "seqIndexColumnIds": [
          "X_7B3TtFbetrabTVnrbFV"
        ],
        "unique": false,
        "meta": {
          "updateAt": 1736702707958,
          "createAt": 1736702707958
        }
      }
    },
    "indexColumnEntities": {
      "bvXUeH-3VL9RDjUWhyIDD": {
        "id": "bvXUeH-3VL9RDjUWhyIDD",
        "indexId": "_1Z0QCT9wykLMBDGwmPY9",
        "columnId": "ujRb3EvYOYxMco1d_BGya",
        "orderType": 1,
        "meta": {
          "updateAt": 1736702707957,
          "createAt": 1736702707957
        }
      },
      "Jv3gUWL4GJHOVM8FFTcC6": {
        "id": "Jv3gUWL4GJHOVM8FFTcC6",
        "indexId": "_1Z0QCT9wykLMBDGwmPY9",
        "columnId": "NlxNnsXhyui5UGSYZ31IV",
        "orderType": 1,
        "meta": {
          "updateAt": 1736702707957,
          "createAt": 1736702707957
        }
      },
      "8PYpdgEoe43SnaPTypdoI": {
        "id": "8PYpdgEoe43SnaPTypdoI",
        "indexId": "os9NW01l8H4Gna6ODq15Y",
        "columnId": "zkYpoxxY_wQ8oFXe7QxcM",
        "orderType": 1,
        "meta": {
          "updateAt": 1736702707957,
          "createAt": 1736702707957
        }
      },
      "zOnjlH8EJIh4puhCncrmV": {
        "id": "zOnjlH8EJIh4puhCncrmV",
        "indexId": "os9NW01l8H4Gna6ODq15Y",
        "columnId": "gQDwcYL8XdTr4DbT3JEND",
        "orderType": 1,
        "meta": {
          "updateAt": 1736702707957,
          "createAt": 1736702707957
        }
      },
      "4_8jVskg-mk7cJq4dAl89": {
        "id": "4_8jVskg-mk7cJq4dAl89",
        "indexId": "os9NW01l8H4Gna6ODq15Y",
        "columnId": "xBnMXdsxV3BPD78boihEv",
        "orderType": 1,
        "meta": {
          "updateAt": 1736702707957,
          "createAt": 1736702707957
        }
      },
      "Nja_C13sqglMFNwW0Lvcz": {
        "id": "Nja_C13sqglMFNwW0Lvcz",
        "indexId": "vDbYEE0Td6tmT1LAo__F1",
        "columnId": "3ia5CK-15TX_ZMuSzNdob",
        "orderType": 1,
        "meta": {
          "updateAt": 1736702707957,
          "createAt": 1736702707957
        }
      },
      "V6MWJDWqVFXqOJw1rxB6_": {
        "id": "V6MWJDWqVFXqOJw1rxB6_",
        "indexId": "GQeDEwbWBv53XAZOa3-6r",
        "columnId": "6yeij-QjJmRubLk-SxQXe",
        "orderType": 1,
        "meta": {
          "updateAt": 1736702707957,
          "createAt": 1736702707957
        }
      },
      "biDrvMwRk0ERNOnjxcXOr": {
        "id": "biDrvMwRk0ERNOnjxcXOr",
        "indexId": "lxHCGWl7d3c-4vjPLTTZW",
        "columnId": "nYGBxDGn0ERdfDkAKJO5R",
        "orderType": 1,
        "meta": {
          "updateAt": 1736702707957,
          "createAt": 1736702707957
        }
      },
      "GadMkXXCtysOic5AfURyu": {
        "id": "GadMkXXCtysOic5AfURyu",
        "indexId": "ROQiKfkchgNQ9lum0u_LU",
        "columnId": "nYGBxDGn0ERdfDkAKJO5R",
        "orderType": 1,
        "meta": {
          "updateAt": 1736702707957,
          "createAt": 1736702707957
        }
      },
      "ALiCSzJAGhACwCbXd96Cn": {
        "id": "ALiCSzJAGhACwCbXd96Cn",
        "indexId": "ROQiKfkchgNQ9lum0u_LU",
        "columnId": "mDrP6teVkoodXGBiHfJUe",
        "orderType": 1,
        "meta": {
          "updateAt": 1736702707957,
          "createAt": 1736702707957
        }
      },
      "mBkypjbO4mL86AvDL-6AY": {
        "id": "mBkypjbO4mL86AvDL-6AY",
        "indexId": "ROQiKfkchgNQ9lum0u_LU",
        "columnId": "vC-djrn-FRk9OyQjMaCns",
        "orderType": 1,
        "meta": {
          "updateAt": 1736702707957,
          "createAt": 1736702707957
        }
      },
      "_qoXwKtBuMliUh9jS-jHn": {
        "id": "_qoXwKtBuMliUh9jS-jHn",
        "indexId": "4iql7GHsUbPfQ-8IgAQP4",
        "columnId": "-jTVx9Bs0kqh0Ky9HIWLO",
        "orderType": 1,
        "meta": {
          "updateAt": 1736702707957,
          "createAt": 1736702707957
        }
      },
      "9jA556-ttukONbrhQKeX4": {
        "id": "9jA556-ttukONbrhQKeX4",
        "indexId": "NB-RmcIf6ALnb61mO8awi",
        "columnId": "VRBHotfED0rJ-F8df492d",
        "orderType": 1,
        "meta": {
          "updateAt": 1736702707957,
          "createAt": 1736702707957
        }
      },
      "zUuwx7BXLkMq2HNZ9jXul": {
        "id": "zUuwx7BXLkMq2HNZ9jXul",
        "indexId": "8cVenpI_1ESF5TY5PaM89",
        "columnId": "20IEpBfSw605VyedgdRu6",
        "orderType": 1,
        "meta": {
          "updateAt": 1736702707957,
          "createAt": 1736702707957
        }
      },
      "-XMUbNvQIrD2pdMcMCbX_": {
        "id": "-XMUbNvQIrD2pdMcMCbX_",
        "indexId": "lPk3mfR8dzC4qUD4emTgA",
        "columnId": "olq7d54JcM9-pfnyuEjfD",
        "orderType": 1,
        "meta": {
          "updateAt": 1736702707957,
          "createAt": 1736702707957
        }
      },
      "A5wn8e8-tZjb_1-v885er": {
        "id": "A5wn8e8-tZjb_1-v885er",
        "indexId": "Mx5c2xDEuWE4m4hzYeQPR",
        "columnId": "uLurIyYTqHdPyrK2lk66H",
        "orderType": 1,
        "meta": {
          "updateAt": 1736702707957,
          "createAt": 1736702707957
        }
      },
      "aoLIjL9GX6RAyCt5a-MKx": {
        "id": "aoLIjL9GX6RAyCt5a-MKx",
        "indexId": "3wXtuYKjLJ9P0YDpkTG6c",
        "columnId": "qt9F3TQ07Ot8EQFHYnqFc",
        "orderType": 1,
        "meta": {
          "updateAt": 1736702707957,
          "createAt": 1736702707957
        }
      },
      "62Mslukj6KjDyLvO1dTSa": {
        "id": "62Mslukj6KjDyLvO1dTSa",
        "indexId": "IXIlEjpm7H0op1E45opbw",
        "columnId": "lhEwzoXcgOL84TcjnGUze",
        "orderType": 1,
        "meta": {
          "updateAt": 1736702707957,
          "createAt": 1736702707957
        }
      },
      "6svYBCwGBsY3egYFIMdCG": {
        "id": "6svYBCwGBsY3egYFIMdCG",
        "indexId": "iqgQOG2lKNY6X2euWjYLw",
        "columnId": "16p46SJ5NllCORM8Q9zEw",
        "orderType": 1,
        "meta": {
          "updateAt": 1736702707958,
          "createAt": 1736702707958
        }
      },
      "3HhyLUreDudy6g3DEfLYv": {
        "id": "3HhyLUreDudy6g3DEfLYv",
        "indexId": "FtfUYi84Zm0v5zf7mXvUp",
        "columnId": "g1rwiOXt0w72YMkqq-HHd",
        "orderType": 1,
        "meta": {
          "updateAt": 1736702707958,
          "createAt": 1736702707958
        }
      },
      "X_7B3TtFbetrabTVnrbFV": {
        "id": "X_7B3TtFbetrabTVnrbFV",
        "indexId": "zgJfD-iclW_Uk-tMJ9fkz",
        "columnId": "eoz9pYj0kfTXNHdqgF8ZR",
        "orderType": 1,
        "meta": {
          "updateAt": 1736702707958,
          "createAt": 1736702707958
        }
      }
    },
    "memoEntities": {}
  },
  "lww": {
    "-R2yuTAMLKpUrH9WsHNm4": [
      "tableEntities",
      -1,
      1736702719252,
      {}
    ],
    "p_eNM2JtN4Qkti5xh_j-v": [
      "relationshipEntities",
      -1,
      1736702731891,
      {}
    ],
    "zWvLS_X29EtgYHLoUauw0": [
      "relationshipEntities",
      -1,
      1736702731891,
      {}
    ],
    "SqYiebLmcDURAb6N2ySGi": [
      "tableEntities",
      -1,
      1736702731891,
      {}
    ],
    "t-7kJta5v01NuAdhC0h9g": [
      "relationshipEntities",
      -1,
      1736702732963,
      {}
    ],
    "PSixUObidiBMOuyFkpVx-": [
      "tableEntities",
      -1,
      1736702732963,
      {}
    ],
    "nYMkVPha8876Ydb9JLfWN": [
      "tableEntities",
      -1,
      1736702734515,
      {}
    ],
    "NB-RmcIf6ALnb61mO8awi": [
      "indexEntities",
      -1,
      1736702757387,
      {}
    ],
    "FP9pvGnaKSAM2BqpEAXPU": [
      "tableEntities",
      -1,
      1736702757387,
      {}
    ]
  }
}